{"prtected": {}, "signature": "None", "payload": {"device_name": "6bf5baf3", "device_type": 1, "sensors": [{"name": "audio", "units": "wav"}], "values": [0, 1, 1, -2, -3, -3, -2, -2, -3, -3, -3, -3, -1, 0, -2, -3, -1, -1, -3, -1, 0, 0, 1, -2, -3, -3, 0, 1, 0, 1, -2, -4, 0, 2, 1, 3, 1, 4, 4, -1, -3, -1, 0, 2, 3, 2, 3, 1, 0, 0, 1, 2, 0, 0, 2, 3, 1, 0, 0, 1, -2, -1, 0, 1, 1, 0, 1, 0, 1, 1, -2, 0, 1, 0, -2, -2, -1, -3, -1, -2, -4, -2, 1, 0, 0, 0, -1, -4, -1, 0, 0, 0, 1, 3, 3, 2, 0, 2, 2, 1, -2, -1, 0, 0, 0, 0, 0, 1, 1, 0, 0, 1, 1, 2, 3, 4, 0, -3, 0, 0, 0, 0, 0, 1, -2, -3, -1, 0, 0, 0, 1, 4, 5, 4, 1, 1, 0, 1, 0, 0, 1, -2, -3, -5, -2, 1, -1, 0, 0, 0, 0, 0, -1, 0, 2, -2, -3, -3, -3, -1, 0, 1, -2, -3, 0, 0, 0, 1, 2, 1, 0, 1, 0, 2, 2, 2, 2, 0, 1, 2, 1, 1, 1, 1, 0, -1, 0, 1, 0, 0, 1, 0, 1, 0, -1, 2, 1, 0, 1, 1, -2, -1, 0, 1, 1, 0, 2, 1, -1, 0, -2, -2, 0, 0, 4, 1, 0, -1, 0, 0, 1, -1, -3, 0, 1, 0, -2, -3, -1, 1, -2, -4, -1, 1, 0, 2, 0, -1, 2, 2, 0, 0, 2, 2, 1, 1, 0, 0, 0, 1, 2, 2, 1, 1, 2, 1, 2, 0, 2, 4, 0, 0, 0, 3, 2, -2, -2, -2, -3, -2, -3, -3, -2, -3, -2, -2, -3, -2, -1, 2, 1, 0, 0, 0, 1, -2, -3, -3, -3, -3, -4, -3, -3, -1, 0, 1, 1, 1, 1, -3, -1, 1, 0, 0, 0, 0, 0, 0, 0, 1, 0, 0, 2, 3, 2, 2, 2, 2, 2, 1, 0, 0, 2, 3, 1, 0, 1, -1, -3, -2, -3, -1, 0, 0, 1, 3, 1, 1, -1, 0, 1, 1, -2, -1, 1, -2, -3, -3, -3, -1, 0, -1, 1, 3, 1, 0, 1, 0, 0, 0, 0, 0, 0, 1, 2, 3, 1, 1, -2, -1, 0, 0, 0, 1, 1, 0, 0, 0, 0, 2, 2, 1, 0, 0, 1, -2, -2, -2, -3, -4, -1, -2, -2, 1, 1, 1, 0, 1, 0, 0, 0, 1, 1, 0, 0, 0, 0, 0, -2, -1, 0, 1, -2, -1, 1, 0, -1, -4, -1, 0, 0, 1, 0, 0, 0, 0, 0, 0, 0, 0, 0, 0, 0, 1, 1, 0, 0, 1, 1, 0, 0, 2, 1, 0, 1, 0, 0, 0, 0, 0, 0, 0, 0, 0, 0, 0, 1, 0, 0, 0, 0, 1, 3, 1, 0, 1, -2, -1, 1, -1, 1, 1, 0, 0, 1, 0, 0, 0, 0, 0, 1, 0, 0, 1, -2, -1, 0, 1, -2, -3, -2, -3, -1, 1, -2, -1, 0, -1, 0, 0, 0, 0, 0, 0, 1, 1, -2, -1, 0, 0, 1, 0, 0, 1, 0, 0, 0, 1, -1, -3, -3, -1, 1, -1, 1, -2, -1, 1, 0, 0, 1, 1, 0, 1, 1, -2, -3, 0, 0, 0, 0, 0, 0, 1, 1, -1, 1, 1, 0, 1, 1, 0, 0, 0, 1, -2, -1, 0, 0, 0, 0, 1, 2, 2, 2, 1, 0, 1, 0, 1, 0, 1, 0, -1, 0, 0, 0, 0, 0, 0, 1, 0, 0, 0, 0, 0, 0, 0, 0, 2, 1, 0, 0, -1, 0, 1, 1, -2, -3, -2, -3, -1, 0, 0, 1, 0, 0, 1, -1, -3, -3, -1, 1, 1, -2, -1, 0, -1, 2, 1, 0, 2, 2, 1, 0, 2, 1, 1, 1, 0, -1, -1, 0, 0, 0, 0, 0, 0, 0, 0, 0, 0, 0, 2, 1, 0, 1, 0, 0, 0, 2, 3, 0, 0, 1, 0, 2, 2, 0, 0, 0, 0, 0, 1, 0, 0, 0, 0, 0, 1, 1, 0, 0, 0, 0, -3, -1, 0, 0, 0, 2, 2, -2, -3, -2, -3, -2, -3, -1, 0, 0, 1, 0, 0, 0, 1, 0, -2, -1, 0, 0, 0, 0, 0, 1, 0, 0, 0, -1, 0, 1, 2, 2, 1, 0, 1, 1, 0, 0, 0, 1, 2, 1, 0, 2, 2, 3, 1, 0, 1, 0, 0, 0, 0, 0, 2, 1, -1, 2, 1, 0, 1, 0, 1, 0, 0, 0, 0, 0, -2, 0, 1, 1, 1, -2, -3, -4, -1, 1, 0, 2, 2, -2, -3, -3, -1, 0, -1, 0, 0, 0, 1, -2, -1, 0, -1, 2, 1, 0, 0, 0, 0, 1, -2, -3, 0, 0, 0, -3, -1, 0, 0, 1, -1, 2, 0, 0, 1, -1, 0, 0, 1, 2, 2, 2, 2, 2, 2, 1, 0, 1, 0, 1, 3, 1, 0, 2, 1, 0, 0, 0, 2, 1, -1, -2, -3, -1, 0, 0, 1, 0, 1, -3, -1, 2, -2, -1, -3, -1, 0, 0, 1, -3, 0, 0, 1, 3, 0, 1, 1, -3, -1, 0, 0, 1, 0, 1, -2, -1, 0, 0, 0, 2, 3, 2, 1, -2, -1, 0, 1, 2, 2, 1, 0, 1, 0, -1, 1, 2, 0, 0, 0, 4, 3, 3, -1, -3, -1, 1, 2, 2, 3, 2, 2, 1, 0, 0, 0, 0, 1, -2, -1, 1, 0, 1, 0, -1, 0, 0, 1, -2, -1, 1, -1, 0, 0, 0, 0, 0, 0, 0, 0, -2, -1, -1, -4, -1, 0, 0, 0, 0, 0, -3, 0, 1, 0, -2, -1, 0, 0, -2, -1, 1, 0, 1, -3, -1, -2, -1, 1, 0, 1, 0, 1, 0, 0, 1, 1, 0, 1, 0, -1, 0, 0, 0, 1, 0, 0, 0, 0, 0, 0, 0, 0, 0, 0, 0, 0, 1, 0, -2, -4, -1, 2, 1, 1, -2, -1, 1, -2, -1, 0, 0, -1, 1, 2, 1, -2, -4, -1, 2, 2, 2, 1, 1, 2, 0, 0, 0, 2, 3, 0, 2, 1, 0, -1, 1, 2, 1, 0, 0, 0, 1, 2, 1, 0, 0, 0, 1, 0, -2, -1, 2, 1, 0, 0, -3, 0, 1, 0, 1, 1, -1, -3, -3, -3, -3, -3, -4, -1, -2, -3, -3, -4, -1, 0, 1, -2, -1, 0, 1, -1, -4, -2, -3, -1, 0, 0, 0, 0, 0, -1, 2, 2, 2, 3, 1, 1, 0, 1, 6, 3, 0, 0, 1, 5, 6, 3, 3, 2, 2, 1, 2, 1, 0, 2, 2, 1, 0, 2, 2, -2, -2, -3, -1, 1, -2, -3, -3, -2, 2, 1, 1, -2, -1, 1, 0, -1, -2, -2, -3, -2, 0, -1, -3, -2, -3, -1, 0, 1, -1, -2, -2, -3, -1, 0, -1, -3, 0, 0, -1, 0, 0, 0, 0, 0, -2, -1, 1, 0, -2, -3, -1, 1, 1, -1, 0, 2, 3, 2, 1, -2, -1, 1, 0, 0, 1, 2, 1, 1, 1, -2, -1, 0, 0, 2, -2, -2, -2, -3, -3, 0, -1, -4, -1, -2, -3, -3, -1, 1, 2, 0, 0, 0, 0, 1, 0, 0, 1, 0, 0, 0, 0, 0, 0, 1, 1, 0, 0, 1, -2, 0, 1, -1, 0, 0, 3, 1, -1, 1, 2, 3, 1, 0, 0, 1, 0, -1, 1, 1, 0, 2, 0, 1, 0, 2, 3, 1, 1, 0, 0, 0, 1, 1, 0, 0, 0, 0, 1, 0, 0, 0, 0, 0, 0, 1, 3, 2, 3, 2, -1, 0, 2, 2, 2, 2, 2, 2, 2, 1, 0, 0, 1, 1, -1, 2, 2, 2, 2, 1, 0, 1, 0, 0, 0, 0, 0, 1, 1, -2, -1, 2, 1, -2, -2, -4, -7, -3, -3, -3, -3, -3, -2, -5, -4, -3, -2, -2, -3, -3, -3, -4, -5, -6, -5, -3, -4, -3, -3, -2, -1, 1, -2, -3, -1, 1, -2, -2, -1, 1, 3, 2, 1, 0, 0, -1, 1, 2, 2, 2, 2, 2, 2, 2, 2, 4, 3, 2, 3, 0, 2, 2, 2, 2, 3, 1, -1, 1, 2, 3, 0, 2, 2, 1, 1, 1, 0, 0, 1, 0, 1, -1, -3, 0, -2, -2, 1, -2, 0, 0, 0, 0, 0, 0, 1, -2, -1, 0, 0, -2, -1, 0, -1, 2, 1, 0, 0, 0, 0, 0, 1, 2, 3, 1, 1, 3, 2, 3, 2, 1, 0, 1, 0, 0, 1, 0, 1, 0, 1, 3, 1, 1, -1, -3, -3, 0, -1, -3, -2, -3, 0, 0, -5, -6, -4, -3, -3, -4, -1, 0, 0, -2, -1, 1, -1, -5, -4, -3, -1, 1, 1, -2, -1, 1, 2, 2, 1, 1, 1, 1, 0, 2, 1, 1, 1, 1, 0, 1, 2, 1, 0, 0, 1, 2, 3, 2, 2, 2, 2, 2, 2, 2, 3, 1, 0, 1, 2, 3, 2, 2, 3, 2, 2, 1, 1, 3, 2, 3, -1, -2, -3, -1, 0, 1, -1, -4, -1, 0, 0, 0, 0, 1, -1, -3, 0, -2, -2, -3, -3, -3, 0, -1, -3, -2, -3, -1, 0, 0, 2, -1, -4, -2, -3, -3, 0, -1, -3, -2, -3, 0, 1, -2, 0, 1, 0, -1, -3, -1, 1, 1, 0, 1, 1, 0, 0, -2, -1, 0, 2, 1, -1, 1, 3, 3, 2, 1, 0, 0, 0, 0, 0, 0, 0, 0, -1, 2, 3, 2, 1, 0, 2, 2, 1, 2, 3, 1, 0, 1, 0, 0, 0, 0, 0, 0, 0, 0, 0, -1, 1, 1, 0, 1, 0, 2, 1, 0, 0, 0, 0, -2, -3, -3, -4, -1, 0, 0, 1, 0, 2, 3, 1, 1, -1, -3, -1, 1, -1, -3, -3, -2, -3, -1, 0, 0, -1, -3, -1, 1, 0, -3, -1, 0, 0, 1, 0, -2, -1, 0, 0, 0, -1, 1, 2, 2, 3, 2, 1, 0, 1, 0, 1, 0, 1, 0, 0, 0, 0, 1, 3, 1, -2, -1, 1, 0, 1, 1, 0, 0, 0, 0, 0, 0, 0, 0, 1, 1, 0, -1, 1, 1, 0, 0, 1, 1, 1, -1, -1, 1, -2, -3, -1, 0, 0, 1, 2, -2, -1, 0, 0, 0, 1, 3, 3, 2, 0, 0, 1, 0, 1, 2, 0, 0, 2, 0, 0, 1, 1, 3, 1, 0, 0, 0, 1, 0, 1, -1, -4, -1, 0, 0, -1, 0, 3, 3, 0, 0, 0, 0, 0, 1, -2, -1, 1, 1, 1, 0, 0, -2, -3, -3, -3, -3, -3, -3, -2, 1, 0, 0, 0, 0, 0, 1, 0, 1, -1, -3, -3, -1, -1, 2, 2, 2, 2, 2, 1, 0, 1, 1, 1, -1, 1, 1, 0, 0, 0, 0, -2, -3, -1, 0, -2, -1, 0, 1, 2, 1, 1, -1, -3, -1, 0, 0, 0, 0, 0, -1, 1, 2, 3, 1, 0, 1, 1, 0, 1, -1, -6, -2, 0, 1, 2, 0, 0, -1, 2, 1, -2, -2, -2, -1, 1, -2, 0, -1, -4, -1, 2, 0, 0, 1, 0, 1, 0, 0, 1, -2, -1, 1, 0, -1, 1, 3, 0, 1, 3, 0, 1, 2, 2, 2, 2, 2, 1, 3, 1, 2, 1, 1, 1, 0, 0, 0, 0, 2, 1, 1, -1, -4, -2, 0, 0, 0, 0, 0, 0, 0, -2, -4, -1, 0, 0, 0, 1, 0, 1, -2, -2, -3, -3, -2, -3, -1, 0, 0, 1, -2, -3, -1, 0, 0, 0, 1, -2, -3, -3, -1, 0, 0, 0, 1, 2, 2, 2, 0, 1, 0, 0, 0, 0, 0, 1, 1, 0, 1, 0, 2, 1, 0, 0, 0, 1, 3, 1, 0, 0, 0, 0, -3, -2, 1, -1, -3, 0, 2, 3, 5, 3, 1, 0, 0, -1, -1, -1, -1, -1, -1, -1, -2, -1, -1, -1, 0, -2, -4, -4, -4, -1, 0, -3, -1, 0, 2, 3, 2, 1, 1, 1, 3, 2, 1, 2, 1, 1, -2, -3, -3, -4, -1, -3, -4, -1, 2, 1, 0, 0, 3, 2, 0, -1, -3, -2, -1, 0, -4, -5, -2, 0, 0, 0, 0, 1, 1, 2, 3, 1, 0, 1, 1, 1, 1, 3, 1, 2, 3, 3, 1, -2, -3, -3, 1, 1, 1, 1, 2, -1, -2, -2, -2, -1, -3, 0, 1, 1, 1, 0, 0, 0, 0, 1, 1, 0, 0, 0, 1, 4, 6, 10, 12, 12, 12, 14, 12, 10, 10, 10, 10, 9, 10, 11, 10, 12, 6, 0, 0, -3, -5, -6, -5, -5, -6, -6, -6, -6, -6, -9, -10, -12, -11, -9, -7, -3, 0, 4, 7, 4, -1, -4, -5, -7, -7, -7, -7, -6, -5, -6, -10, -11, -18, -19, -23, -30, -31, -34, -37, -38, -40, -43, -46, -50, -50, -52, -54, -53, -54, -52, -49, -45, -39, -35, -31, -31, -29, -25, -24, -19, -11, -4, 1, 7, 14, 18, 21, 23, 27, 29, 32, 37, 42, 50, 52, 56, 58, 60, 63, 66, 69, 65, 63, 65, 67, 69, 72, 75, 79, 80, 83, 82, 82, 86, 88, 91, 94, 98, 99, 100, 103, 104, 104, 102, 106, 105, 103, 100, 96, 98, 97, 94, 94, 90, 82, 78, 74, 69, 64, 60, 56, 52, 44, 36, 35, 28, 16, 2, -11, -28, -46, -63, -83, -107, -136, -167, -203, -237, -272, -311, -347, -391, -434, -475, -518, -560, -596, -632, -660, -682, -711, -730, -749, -760, -764, -762, -748, -731, -708, -685, -661, -632, -599, -557, -512, -454, -394, -335, -269, -206, -141, -72, -5, 61, 131, 191, 247, 299, 350, 401, 445, 494, 545, 588, 631, 675, 715, 757, 805, 861, 925, 991, 1062, 1129, 1196, 1256, 1306, 1356, 1403, 1437, 1461, 1479, 1481, 1472, 1455, 1434, 1406, 1379, 1349, 1308, 1262, 1217, 1165, 1106, 1046, 989, 935, 878, 822, 765, 702, 638, 571, 510, 446, 377, 303, 221, 133, 41, -64, -175, -286, -402, -517, -638, -768, -900, -1029, -1156, -1278, -1393, -1498, -1601, -1704, -1804, -1899, -1986, -2072, -2154, -2234, -2308, -2376, -2439, -2490, -2530, -2559, -2579, -2585, -2583, -2573, -2551, -2514, -2468, -2415, -2348, -2268, -2173, -2066, -1945, -1809, -1661, -1502, -1326, -1142, -950, -754, -561, -370, -177, 9, 184, 340, 477, 598, 699, 785, 859, 924, 983, 1040, 1101, 1173, 1255, 1359, 1479, 1619, 1779, 1953, 2155, 2372, 2591, 2810, 3021, 3215, 3387, 3529, 3638, 3709, 3741, 3734, 3689, 3612, 3501, 3369, 3224, 3061, 2884, 2696, 2500, 2300, 2101, 1912, 1731, 1566, 1418, 1277, 1141, 999, 856, 708, 548, 386, 218, 39, -140, -324, -503, -672, -839, -992, -1135, -1279, -1432, -1596, -1768, -1940, -2102, -2245, -2366, -2463, -2546, -2630, -2720, -2828, -2943, -3062, -3180, -3293, -3396, -3478, -3545, -3592, -3609, -3597, -3562, -3506, -3445, -3393, -3358, -3340, -3318, -3274, -3193, -3057, -2871, -2644, -2397, -2145, -1900, -1667, -1438, -1215, -994, -786, -600, -442, -299, -163, -17, 142, 316, 495, 668, 834, 997, 1185, 1436, 1770, 2192, 2690, 3229, 3773, 4283, 4730, 5101, 5395, 5604, 5722, 5755, 5701, 5557, 5345, 5085, 4803, 4511, 4204, 3867, 3500, 3101, 2680, 2257, 1870, 1549, 1303, 1129, 1003, 890, 776, 644, 488, 325, 166, 24, -89, -169, -214, -226, -212, -177, -125, -84, -66, -86, -154, -265, -408, -563, -719, -861, -992, -1110, -1245, -1399, -1571, -1756, -1929, -2073, -2170, -2213, -2201, -2141, -2053, -1952, -1852, -1768, -1714, -1684, -1676, -1688, -1709, -1733, -1747, -1758, -1766, -1768, -1776, -1790, -1811, -1835, -1858, -1862, -1847, -1827, -1822, -1856, -1941, -2089, -2271, -2471, -2636, -2742, -2780, -2745, -2649, -2503, -2322, -2142, -1966, -1820, -1743, -1757, -1853, -1999, -2138, -2221, -2200, -2068, -1842, -1543, -1199, -808, -337, 247, 971, 1836, 2809, 3816, 4793, 5681, 6438, 7055, 7513, 7808, 7930, 7870, 7621, 7208, 6675, 6094, 5537, 5033, 4577, 4134, 3653, 3103, 2493, 1863, 1275, 794, 459, 265, 177, 149, 133, 111, 79, 52, 29, -12, -85, -194, -329, -463, -557, -569, -490, -322, -101, 122, 304, 436, 514, 539, 524, 454, 315, 85, -243, -652, -1104, -1561, -1966, -2287, -2504, -2623, -2659, -2633, -2558, -2439, -2282, -2089, -1866, -1630, -1400, -1220, -1095, -1041, -1050, -1115, -1226, -1378, -1562, -1757, -1959, -2150, -2306, -2411, -2446, -2420, -2368, -2324, -2334, -2427, -2616, -2880, -3182, -3465, -3698, -3857, -3935, -3943, -3895, -3788, -3617, -3388, -3099, -2776, -2458, -2174, -1943, -1768, -1655, -1582, -1538, -1532, -1567, -1606, -1592, -1424, -1003, -274, 775, 2068, 3487, 4891, 6146, 7167, 7938, 8464, 8783, 8927, 8899, 8724, 8430, 8052, 7636, 7205, 6770, 6300, 5742, 5046, 4206, 3255, 2286, 1411, 730, 293, 80, 41, 97, 172, 216, 232, 224, 208, 189, 145, 70, -50, -205, -344, -425, -412, -293, -71, 232, 576, 915, 1218, 1452, 1596, 1619, 1492, 1190, 708, 83, -629, -1340, -1965, -2458, -2782, -2944, -2986, -2939, -2840, -2707, -2535, -2331, -2096, -1846, -1593, -1364, -1166, -1005, -878, -796, -788, -874, -1078, -1406, -1827, -2278, -2685, -2970, -3097, -3078, -2971, -2856, -2809, -2883, -3082, -3356, -3640, -3869, -4028, -4126, -4169, -4193, -4191, -4121, -3943, -3639, -3229, -2762, -2325, -1973, -1722, -1536, -1346, -1112, -851, -658, -665, -955, -1500, -2157, -2670, -2781, -2317, -1270, 219, 1914, 3575, 5044, 6269, 7289, 8146, 8853, 9378, 9651, 9633, 9351, 8907, 8439, 8056, 7770, 7490, 7062, 6343, 5283, 3945, 2517, 1228, 250, -349, -613, -683, -715, -789, -921, -1047, -1088, -972, -709, -366, -39, 194, 284, 264, 198, 157, 208, 354, 592, 896, 1236, 1603, 1968, 2307, 2556, 2646, 2508, 2077, 1374, 470, -521, -1445, -2199, -2720, -3002, -3088, -3042, -2931, -2800, -2659, -2508, -2345, -2159, -1949, -1718, -1472, -1221, -972, -758, -594, -528, -608, -844, -1233, -1722, -2260, -2765, -3157, -3394, -3468, -3421, -3324, -3265, -3306, -3469, -3712, -3973, -4180, -4266, -4245, -4180, -4154, -4235, -4417, -4628, -4747, -4673, -4380, -3899, -3357, -2861, -2424, -2022, -1566, -1003, -367, 194, 466, 297, -334, -1242, -2064, -2413, -2002, -797, 1008, 3056, 4975, 6508, 7577, 8278, 8753, 9137, 9458, 9645, 9630, 9359, 8891, 8344, 7851, 7479, 7169, 6770, 6123, 5132, 3836, 2415, 1110, 149, -366, -471, -323, -147, -115, -276, -575, -881, -1029, -936, -618, -187, 195, 396, 353, 115, -191, -405, -413, -157, 316, 904, 1477, 1943, 2267, 2426, 2423, 2267, 1908, 1329, 517, -460, -1488, -2422, -3102, -3454, -3482, -3273, -2967, -2687, -2520, -2486, -2524, -2529, -2417, -2120, -1652, -1098, -586, -231, -109, -256, -608, -1074, -1563, -1990, -2323, -2559, -2711, -2798, -2841, -2870, -2908, -3013, -3205, -3498, -3880, -4263, -4562, -4692, -4641, -4456, -4214, -4022, -3914, -3887, -3879, -3780, -3559, -3233, -2849, -2468, -2112, -1743, -1305, -806, -313, -6, -78, -645, -1654, -2787, -3628, -3755, -2937, -1219, 1081, 3473, 5543, 7036, 7948, 8459, 8823, 9188, 9554, 9826, 9859, 9587, 9064, 8448, 7901, 7488, 7136, 6641, 5827, 4623, 3118, 1568, 272, -540, -807, -648, -293, 8, 107, -28, -310, -594, -723, -616, -274, 223, 744, 1171, 1416, 1419, 1195, 821, 404, 76, -46, 89, 459, 963, 1474, 1844, 1976, 1829, 1431, 829, 86, -738, -1585, -2388, -3075, -3533, -3699, -3547, -3113, -2520, -1934, -1508, -1310, -1334, -1478, -1578, -1494, -1165, -663, -124, 279, 399, 179, -347, -1066, -1829, -2505, -3015, -3337, -3501, -3536, -3498, -3428, -3347, -3301, -3340, -3490, -3758, -4102, -4453, -4733, -4901, -4949, -4895, -4771, -4605, -4384, -4073, -3655, -3138, -2557, -1990, -1504, -1124, -819, -543, -291, -110, -131, -477, -1213, -2264, -3341, -4105, -4207, -3460, -1936, 110, 2272, 4227, 5781, 6939, 7832, 8584, 9274, 9836, 10185, 10217, 9941, 9459, 8938, 8538, 8239, 7965, 7518, 6731, 5563, 4108, 2614, 1332, 467, 42, -50, 19, 30, -108, -399, -752, -1043, -1159, -1025, -669, -127, 509, 1141, 1660, 1944, 1943, 1655, 1131, 490, -126, -544, -671, -472, -4, 578, 1116, 1464, 1548, 1286, 713, -111, -1092, -2091, -2989, -3625, -3899, -3804, -3383, -2815, -2251, -1859, -1704, -1745, -1876, -1936, -1835, -1507, -1021, -454, 66, 390, 450, 185, -391, -1191, -2111, -3027, -3803, -4336, -4588, -4578, -4366, -4051, -3732, -3490, -3376, -3423, -3603, -3845, -4064, -4197, -4200, -4068, -3832, -3563, -3331, -3144, -3007, -2881, -2760, -2607, -2403, -2143, -1803, -1419, -951, -487, -100, 92, -83, -644, -1535, -2497, -3221, -3388, -2794, -1477, 390, 2443, 4375, 5977, 7195, 8138, 8882, 9533, 10068, 10400, 10468, 10219, 9725, 9147, 8640, 8284, 8036, 7754, 7250, 6388, 5160, 3697, 2255, 1051, 226, -229, -439, -574, -788, -1090, -1445, -1715, -1740, -1466, -928, -218, 545, 1216, 1723, 2040, 2156, 2059, 1719, 1126, 320, -637, -1544, -2187, -2400, -2124, -1467, -619, 99, 500, 509, 155, -385, -994, -1520, -1941, -2280, -2533, -2725, -2791, -2741, -2513, -2151, -1762, -1443, -1290, -1262, -1338, -1357, -1193, -853, -417, -71, 58, -172, -771, -1618, -2558, -3402, -4066, -4489, -4716, -4770, -4669, -4463, -4117, -3696, -3259, -2891, -2703, -2684, -2821, -2959, -3004, -2900, -2642, -2377, -2231, -2343, -2645, -3013, -3253, -3156, -2743, -2095, -1435, -955, -717, -693, -768, -868, -953, -1119, -1483, -2055, -2719, -3167, -3088, -2216, -544, 1721, 4182, 6371, 8019, 9023, 9524, 9747, 9923, 10128, 10307, 10345, 10113, 9625, 8999, 8371, 7868, 7454, 6977, 6270, 5191, 3768, 2165, 628, -592, -1340, -1611, -1523, -1259, -976, -776, -637, -532, -395, -171, 168, 604, 1050, 1483, 1846, 2073, 2103, 1843, 1230, 270, -957, -2225, -3277, -3883, -3908, -3378, -2448, -1383, -437, 210, 483, 387, 24, -456, -974, -1440, -1814, -2094, -2268, -2276, -2102, -1777, -1357, -955, -670, -603, -744, -1014, -1248, -1303, -1143, -770, -351, -85, -121, -588, -1455, -2572, -3671, -4567, -5114, -5231, -5011, -4525, -3941, -3349, -2782, -2295, -1897, -1683, -1642, -1833, -2193, -2625, -3068, -3368, -3514, -3482, -3405, -3316, -3279, -3277, -3223, -3157, -2930, -2598, -2181, -1691, -1243, -849, -719, -850, -1340, -2124, -2988, -3657, -3779, -3208, -1811, 233, 2608, 4990, 7056, 8692, 9859, 10632, 11132, 11374, 11405, 11163, 10658, 9999, 9275, 8645, 8134, 7711, 7243, 6517, 5458, 3992, 2289, 577, -805, -1651, -1912, -1607, -1047, -417, 61, 348, 498, 566, 717, 941, 1251, 1564, 1811, 2035, 2167, 2295, 2310, 2098, 1519, 441, -960, -2543, -3885, -4621, -4578, -3670, -2293, -708, 593, 1347, 1569, 1297, 895, 379, -41, -414, -859, -1273, -1722, -1949, -1962, -1704, -1278, -947, -806, -1052, -1446, -1905, -2156, -2046, -1650, -1048, -630, -519, -913, -1803, -2946, -4165, -5113, -5754, -5981, -5895, -5603, -5141, -4632, -4015, -3425, -2871, -2518, -2427, -2584, -3003, -3463, -3914, -4142, -4156, -3990, -3758, -3672, -3650, -3774, -3846, -3814, -3550, -2998, -2320, -1493, -863, -444, -444, -914, -1695, -2759, -3576, -4013, -3673, -2483, -612, 1837, 4333, 6775, 8875, 10597, 11946, 12777, 13230, 13091, 12547, 11627, 10519, 9536, 8714, 8278, 7961, 7612, 6944, 5764, 4200, 2314, 571, -858, -1722, -2000, -1864, -1430, -1034, -653, -368, -76, 276, 652, 1081, 1394, 1663, 1829, 1987, 2212, 2464, 2777, 2893, 2721, 1999, 736, -949, -2798, -4354, -5355, -5480, -4870, -3666, -2258, -997, -30, 477, 764, 834, 888, 934, 842, 655, 221, -257, -767, -1118, -1188, -1086, -829, -727, -828, -1153, -1617, -1970, -2114, -1840, -1344, -792, -455, -571, -1126, -2131, -3331, -4518, -5413, -5858, -5909, -5572, -5095, -4543, -4051, -3678, -3372, -3198, -3047, -3063, -3154, -3417, -3849, -4324, -4827, -5128, -5285, -5181, -4896, -4560, -4153, -3783, -3339, -2872, -2270, -1586, -1036, -715, -942, -1729, -2946, -4265, -5094, -5093, -3984, -1937, 762, 3632, 6207, 8356, 10027, 11380, 12489, 13330, 13809, 13694, 13014, 11795, 10393, 9162, 8298, 7910, 7673, 7277, 6326, 4717, 2662, 522, -1123, -2050, -2159, -1703, -1052, -527, -329, -350, -415, -242, 241, 978, 1821, 2549, 3030, 3192, 3195, 3219, 3319, 3497, 3536, 3192, 2180, 488, -1667, -3880, -5587, -6436, -6249, -5212, -3720, -2197, -1019, -253, 174, 539, 992, 1475, 1926, 2018, 1663, 898, -59, -851, -1304, -1279, -1024, -802, -873, -1341, -2012, -2655, -2939, -2744, -2121, -1338, -757, -591, -970, -1797, -2881, -3903, -4703, -5218, -5445, -5540, -5559, -5534, -5365, -4984, -4374, -3573, -2824, -2342, -2252, -2631, -3341, -4181, -4872, -5278, -5335, -5137, -4880, -4654, -4556, -4417, -4100, -3466, -2514, -1524, -799, -755, -1582, -3179, -5066, -6530, -6964, -6024, -3810, -784, 2402, 5230, 7494, 9258, 10827, 12359, 13789, 14855, 15223, 14706, 13363, 11585, 9909, 8797, 8357, 8301, 8123, 7341, 5731, 3408, 892, -1226, -2492, -2828, -2443, -1752, -1153, -808, -696, -555, -180, 548, 1544, 2535, 3301, 3663, 3659, 3460, 3294, 3413, 3715, 4044, 4096, 3613, 2487, 691, -1460, -3656, -5493, -6661, -7131, -6834, -6030, -4909, -3669, -2421, -1181, -47, 1039, 1906, 2474, 2680, 2488, 2028, 1382, 791, 323, 3, -222, -539, -997, -1609, -2254, -2767, -3064, -3080, -2843, -2471, -2112, -1928, -1928, -2122, -2467, -2905, -3415, -3910, -4409, -4910, -5326, -5535, -5427, -4988, -4309, -3549, -2945, -2661, -2704, -3059, -3504, -3918, -4198, -4349, -4425, -4476, -4573, -4635, -4723, -4735, -4682, -4518, -4151, -3726, -3284, -3232, -3782, -4972, -6565, -7937, -8484, -7620, -5298, -1900, 2023, 5702, 8721, 11004, 12732, 14192, 15437, 16370, 16646, 16012, 14520, 12357, 10154, 8385, 7328, 6864, 6485, 5728, 4190, 1953, -556, -2722, -3981, -4201, -3560, -2536, -1543, -787, -209, 446, 1367, 2626, 3972, 5084, 5652, 5646, 5265, 4806, 4550, 4526, 4664, 4662, 4233, 3205, 1570, -484, -2771, -4908, -6710, -7975, -8649, -8727, -8211, -7242, -5812, -4071, -2082, -62, 1750, 3187, 4022, 4271, 3975, 3374, 2697, 2046, 1465, 849, 175, -601, -1435, -2159, -2666, -2920, -2988, -2962, -2914, -2902, -2828, -2662, -2418, -2104, -1904, -1900, -2170, -2651, -3229, -3769, -4056, -4099, -3908, -3587, -3310, -3106, -3075, -3158, -3338, -3578, -3801, -4075, -4376, -4734, -5062, -5291, -5391, -5240, -4953, -4612, -4366, -4240, -4063, -3832, -3393, -2973, -2914, -3532, -4954, -6744, -8156, -8423, -7116, -4285, -539, 3327, 6720, 9374, 11393, 13014, 14384, 15537, 16169, 15996, 14872, 12879, 10501, 8339, 6914, 6290, 6111, 5734, 4601, 2522, -153, -2638, -4260, -4636, -3865, -2518, -1137, -60, 729, 1500, 2503, 3855, 5314, 6464, 6919, 6594, 5740, 4859, 4370, 4353, 4636, 4721, 4223, 2974, 1093, -993, -3009, -4711, -6081, -7268, -8195, -8907, -9072, -8621, -7383, -5376, -2937, -200, 2089, 3890, 4951, 5310, 5366, 5014, 4706, 4116, 3290, 2187, 708, -701, -2079, -2871, -3301, -3430, -3316, -3448, -3524, -3788, -3857, -3610, -3156, -2420, -1899, -1539, -1542, -1813, -2151, -2563, -2766, -2950, -3022, -3083, -3251, -3319, -3483, -3484, -3444, -3423, -3369, -3589, -3882, -4438, -5038, -5566, -6004, -6058, -6041, -5792, -5564, -5404, -5088, -4725, -3946, -3037, -2205, -1968, -2844, -4464, -6622, -8042, -8140, -6506, -3265, 537, 4441, 7574, 10043, 12004, 13623, 15175, 16092, 16290, 15208, 13099, 10452, 7798, 6117, 5312, 5450, 5626, 5168, 3854, 1630, -649, -2541, -3321, -3070, -2148, -890, 132, 1140, 2136, 3477, 5140, 6695, 7893, 8143, 7580, 6326, 4977, 4115, 3757, 3862, 3681, 3054, 1751, -41, -1755, -3267, -4164, -4961, -5711, -6646, -7720, -8240, -8213, -7019, -5160, -2879, -503, 1329, 2986, 4051, 5041, 5775, 6138, 6146, 5215, 3926, 2033, 204, -1217, -2246, -2471, -2660, -2664, -2902, -3269, -3404, -3409, -2868, -2352, -1803, -1575, -1734, -1869, -2084, -1942, -1837, -1758, -1905, -2398, -2897, -3409, -3555, -3457, -3072, -2720, -2559, -2581, -3009, -3408, -4039, -4586, -5273, -6204, -7129, -8200, -8577, -8460, -7487, -6014, -4678, -3406, -2873, -2280, -1892, -1583, -1552, -2692, -4448, -6940, -8604, -8726, -6998, -3243, 961, 5307, 8616, 10961, 12681, 13786, 14924, 15449, 15389, 14325, 12287, 9846, 7292, 5664, 4914, 4925, 5002, 4218, 2480, -174, -2742, -4402, -4645, -3551, -1746, 163, 1709, 3024, 4305, 5855, 7520, 8916, 9597, 9213, 7921, 6134, 4514, 3399, 2942, 2660, 2031, 812, -1121, -3157, -4930, -5894, -6074, -5838, -5536, -5542, -5632, -5719, -5220, -4079, -2430, -601, 961, 2277, 3175, 4014, 4819, 5560, 6094, 6039, 5373, 3996, 2157, 167, -1607, -2829, -3437, -3452, -3265, -3110, -3072, -3134, -2977, -2611, -1985, -1376, -1095, -1153, -1434, -1611, -1513, -1180, -919, -908, -1437, -2239, -3207, -3844, -3998, -3784, -3169, -2893, -2704, -3186, -3801, -4427, -5014, -5182, -5777, -6193, -7109, -7641, -7538, -6831, -5145, -3928, -2604, -2088, -1569, -905, -774, -869, -2945, -5749, -9243, -11579, -11551, -9710, -5485, -1425, 2958, 6533, 9620, 12853, 15025, 17307, 17852, 17563, 15913, 13151, 10538, 7480, 5837, 4564, 4121, 3522, 1965, 59, -2750, -4672, -5763, -5255, -3569, -1560, 877, 2803, 5044, 7134, 9287, 11183, 12043, 12027, 10466, 8378, 5867, 3797, 2500, 1637, 1274, 266, -899, -2665, -4285, -5421, -6198, -5979, -5953, -5296, -4721, -3797, -2243, -1041, 693, 1335, 1821, 1752, 1376, 1715, 1588, 2369, 2548, 2745, 2710, 1867, 1523, 338, -103, -733, -1193, -1259, -1923, -1778, -2202, -1811, -1384, -1063, -564, -1228, -1547, -2647, -3170, -3339, -3323, -2399, -2041, -1086, -750, -466, -164, -451, -258, -828, -1085, -1484, -2039, -2010, -2715, -2868, -3611, -4545, -4999, -6234, -6460, -7411, -8166, -8282, -8772, -7198, -5811, -3402, -1119, -445, 543, -411, -438, -651, -1061, -968, -3358, -5305, -8308, -9756, -8704, -6762, -2221, 1126, 4676, 7166, 8701, 11021, 12257, 14366, 15183, 15120, 14000, 11278, 8839, 5899, 4272, 3347, 2888, 2552, 1036, -629, -2630, -3612, -3395, -2092, 65, 1917, 3577, 4694, 5910, 7332, 8802, 10032, 10179, 9330, 7378, 5068, 2960, 1327, 513, -153, -766, -1857, -3242, -4331, -5165, -5031, -4470, -3524, -2444, -1643, -574, 221, 1108, 1772, 2036, 2291, 1968, 1748, 1221, 648, 206, -362, -333, -405, -187, -133, -319, -372, -686, -573, -555, -458, -432, -656, -674, -896, -985, -1250, -1726, -2258, -2976, -3408, -3707, -3744, -3482, -2988, -2127, -1254, -463, -43, -78, -417, -1014, -1634, -2417, -3290, -4222, -5130, -5760, -6232, -6488, -6723, -6984, -6975, -6542, -5479, -4064, -2767, -1803, -1327, -1133, -1056, -1122, -1232, -1517, -1903, -2155, -2375, -2756, -3978, -6199, -8819, -10906, -11176, -9600, -6336, -2274, 1546, 5115, 8092, 10951, 13392, 15194, 16278, 15869, 14363, 11729, 8704, 6049, 3867, 2805, 2398, 2200, 1436, -203, -2139, -3893, -4674, -4188, -2575, -384, 1894, 4081, 6211, 8286, 10089, 11272, 11274, 10124, 8016, 5577, 3186, 1191, -388, -1578, -2590, -3566, -4138, -4438, -4260, -3968, -3595, -3165, -2750, -1773, -456, 1263, 2899, 4014, 4487, 4062, 3120, 1947, 680, -479, -1649, -2669, -3281, -3547, -3191, -2415, -1398, -286, 425, 886, 865, 708, 640, 445, 442, 89, -409, -1110, -2012, -2741, -3363, -3610, -3696, -3684, -3624, -3371, -2813, -2020, -1124, -524, -312, -744, -1549, -2369, -3182, -3527, -4044, -4462, -5179, -5947, -6229, -6377, -5960, -5671, -5158, -4362, -3555, -2361, -1746, -1256, -1247, -1430, -1177, -1178, -1068, -1576, -2330, -2979, -3490, -3595, -4357, -6091, -8533, -10775, -11330, -10088, -7080, -3079, 937, 4851, 8235, 11330, 13872, 15498, 16314, 15751, 14087, 11412, 8405, 5850, 3799, 2770, 2328, 1758, 424, -1786, -3988, -5437, -5517, -4283, -2051, 610, 3440, 6074, 8673, 10915, 12484, 13110, 12137, 9879, 6606, 3360, 618, -1356, -2375, -2830, -2930, -3031, -3170, -3120, -2748, -2061, -1438, -842, -277, 573, 1792, 3196, 4560, 5218, 5078, 3779, 1812, -285, -2201, -3523, -4518, -4879, -4694, -4059, -2995, -1995, -807, 260, 1279, 2007, 2208, 2168, 1623, 973, -5, -1056, -2048, -2976, -3742, -4501, -4969, -5156, -4887, -4199, -3354, -2377, -1612, -975, -656, -699, -943, -1432, -1962, -2552, -3260, -3899, -4615, -4956, -5090, -4969, -4533, -4149, -3652, -3572, -3381, -2988, -2500, -1936, -2162, -2324, -2837, -2728, -2161, -1520, -829, -1252, -1658, -2662, -3048, -2747, -2490, -2645, -4924, -7682, -10217, -10857, -9241, -6421, -2038, 1722, 5286, 7807, 9872, 11936, 13483, 14929, 14809, 13518, 11037, 8074, 5518, 3169, 2035, 1468, 946, -502, -2644, -4194, -4870, -4118, -2290, 430, 3410, 5883, 8025, 9653, 10866, 11487, 11143, 9478, 6627, 3522, 1084, -549, -1466, -1818, -1837, -1796, -2268, -2540, -2420, -1931, -1188, -647, 61, 765, 1824, 3197, 4297, 5217, 5080, 4276, 2557, 277, -1780, -3777, -4975, -5709, -5509, -4643, -3490, -2002, -776, 604, 1689, 2344, 2600, 2339, 1968, 1282, 495, -526, -1580, -2584, -3487, -4011, -4442, -4493, -4462, -4352, -4075, -3623, -2687, -1741, -932, -479, -458, -872, -1489, -2181, -2872, -3368, -3995, -4140, -4351, -4347, -4148, -4168, -3807, -3824, -3468, -3099, -2713, -2266, -2493, -2665, -3265, -3168, -2747, -2156, -1787, -2090, -2097, -2325, -1768, -1094, -472, -698, -3390, -6765, -10409, -12044, -11413, -9084, -5003, -1219, 2590, 5692, 8611, 11553, 13889, 15719, 15714, 13989, 11109, 8010, 5442, 3452, 2520, 2291, 2015, 607, -1337, -3131, -3990, -3586, -2108, 256, 2699, 4979, 7106, 8836, 10323, 11306, 11475, 10313, 7747, 4753, 1998, 42, -936, -993, -536, -457, -669, -980, -923, -489, -14, 453, 853, 1163, 1706, 2665, 3778, 4667, 4762, 3977, 2387, 506, -1174, -2218, -3004, -3718, -4032, -4083, -3562, -2836, -1666, -304, 665, 1392, 1523, 1527, 1384, 1126, 1113, 412, -634, -2170, -3754, -4681, -5257, -4945, -4437, -4012, -3596, -3258, -2542, -1617, -604, 70, -47, -785, -1840, -2785, -3209, -3253, -3094, -2977, -3245, -3457, -3935, -4205, -3912, -3510, -2711, -2728, -2946, -3255, -3682, -3241, -2612, -1784, -1515, -1814, -1741, -1483, -1092, -760, -870, -1357, -2079, -2653, -3210, -5044, -7838, -10161, -11357, -10474, -8515, -5138, -1072, 2438, 6362, 9887, 12858, 14546, 14812, 14625, 13168, 10786, 8339, 5815, 3562, 1670, 999, 1117, 383, -767, -1846, -2471, -2521, -1848, 61, 2335, 4359, 6557, 8692, 10152, 10665, 10464, 9499, 7284, 4515, 2240, 507, -837, -1470, -1125, -491, -231, -106, 17, -82, -311, -170, 603, 1468, 2199, 2966, 3380, 3642, 3722, 3608, 2970, 1138, -925, -2881, -4273, -4900, -4953, -4370, -3893, -3437, -2566, -1408, 83, 1212, 1988, 2306, 1859, 1420, 731, -42, -1042, -2312, -3479, -4670, -5415, -5402, -4862, -4088, -3364, -2560, -1855, -1185, -537, 15, 196, -52, -494, -981, -1521, -1921, -2236, -2738, -3308, -3980, -4271, -4348, -4225, -3769, -3238, -2459, -1951, -1602, -1419, -1424, -1097, -940, -916, -1299, -2174, -2609, -2866, -2633, -2390, -2689, -2879, -3222, -2839, -2418, -2748, -4166, -6733, -8749, -9594, -8589, -5999, -2706, 747, 3713, 6345, 8802, 10933, 12703, 13956, 13921, 12556, 10085, 7236, 4872, 3189, 2792, 2721, 2095, 876, -757, -1932, -2493, -2136, -810, 847, 2603, 4348, 5918, 7260, 8286, 8978, 9008, 7936, 6294, 4577, 2982, 1746, 1069, 1076, 1222, 1015, 549, -123, -878, -1462, -1570, -1245, -685, 116, 1156, 2108, 2794, 3326, 3518, 2919, 1432, -308, -2053, -3668, -4776, -5103, -4755, -4169, -3323, -2274, -1167, -238, 682, 1414, 1508, 1139, 650, 125, -637, -1615, -2383, -3257, -4204, -5017, -5446, -5602, -5632, -5120, -3896, -2519, -1213, -25, 653, 803, 726, 562, 291, -643, -1596, -2487, -3777, -4854, -5568, -5519, -5169, -4729, -3744, -2738, -1688, -615, 111, 507, 350, 184, -4, -789, -1687, -2618, -3431, -3889, -3928, -3026, -2281, -1994, -2042, -2263, -2059, -1756, -1854, -3295, -6042, -8398, -9332, -8491, -6397, -3378, -70, 2851, 5497, 7973, 10201, 11906, 13074, 13542, 12832, 10975, 8716, 6542, 4754, 3720, 3308, 2751, 1381, -430, -1888, -2807, -2966, -2141, -511, 1429, 3211, 4820, 6142, 7079, 7875, 8439, 8505, 7826, 6695, 5369, 4184, 3296, 2911, 2691, 1874, 631, -814, -2056, -2898, -3047, -2344, -1427, -513, 189, 701, 1159, 1494, 1940, 2055, 1540, 578, -468, -1232, -1789, -2184, -2576, -3012, -3401, -3446, -3065, -2459, -1857, -1339, -895, -515, -10, 475, 635, 273, -467, -1486, -2672, -3777, -4657, -5079, -5186, -4879, -4081, -3263, -2295, -1430, -524, 348, 774, 876, 164, -1090, -2360, -3593, -4231, -4837, -5015, -4922, -4731, -4139, -3655, -2902, -2201, -1737, -1342, -1459, -1303, -1138, -1059, -740, -829, -973, -1454, -1957, -1861, -2168, -2431, -2887, -3407, -3055, -2629, -1886, -2530, -4973, -7602, -9845, -10004, -8599, -5939, -2085, 1149, 4486, 7488, 10220, 12887, 14642, 15708, 15101, 12615, 9619, 6439, 4130, 3087, 2952, 3142, 2153, 376, -1404, -3082, -3937, -3752, -2117, 388, 2659, 4744, 6354, 7667, 8993, 10103, 10597, 9794, 8116, 6221, 4417, 3119, 2541, 2438, 1816, 534, -1106, -2534, -3531, -4121, -3978, -3429, -2650, -1651, -569, 626, 1694, 2848, 3650, 3387, 2307, 930, -133, -839, -1235, -1529, -2148, -3079, -3778, -4074, -3956, -3435, -2666, -1806, -1191, -470, 338, 987, 1076, 649, -166, -1516, -2936, -4135, -4793, -5047, -4938, -4297, -3611, -2741, -1872, -1038, -295, 98, 326, -18, -662, -1405, -2189, -2810, -3681, -4391, -4859, -5123, -4985, -4771, -4103, -3249, -2215, -1013, -474, -231, -402, -590, -536, -613, -639, -998, -1692, -2152, -2692, -2931, -3171, -3479, -3380, -3306, -2882, -2845, -4101, -5967, -7811, -8459, -7572, -5718, -2829, 248, 3519, 6749, 9266, 11349, 12643, 13638, 13884, 12728, 10728, 8409, 6362, 5010, 4194, 3845, 3097, 1626, -83, -1855, -2972, -3200, -2324, -462, 1506, 3575, 5510, 6948, 8130, 9026, 9611, 9431, 8370, 6976, 5465, 4187, 3318, 2769, 2192, 1090, -328, -2031, -3530, -4489, -4721, -4353, -3647, -2593, -1359, -54, 1164, 2253, 3133, 3376, 3088, 2071, 623, -740, -1835, -2415, -2983, -3462, -3940, -4414, -4439, -4106, -3226, -2195, -1402, -696, -221, 180, 397, 184, -306, -1284, -2337, -3319, -4201, -4583, -4590, -4037, -3169, -2411, -1607, -1030, -575, -180, -3, -34, -435, -1179, -2058, -3031, -3823, -4404, -4745, -4871, -4854, -4611, -3979, -3119, -2050, -984, -3, 556, 567, 248, -176, -678, -1042, -1639, -2358, -3237, -3470, -3022, -2159, -1515, -1311, -1577, -2059, -2515, -3061, -4507, -6448, -8169, -8810, -8143, -6261, -3274, 106, 3581, 6707, 9043, 10626, 11677, 12646, 13317, 13104, 11947, 10277, 8333, 6573, 5038, 3736, 2199, 395, -1519, -3255, -4371, -4448, -3111, -710, 1966, 4362, 6207, 7450, 8294, 9005, 9515, 9368, 8562, 7380, 6061, 4852, 3818, 2948, 1905, 296, -1671, -3736, -5363, -6125, -5841, -4717, -3246, -1800, -292, 1098, 2417, 3536, 4223, 4375, 3804, 2771, 1385, -403, -2040, -3477, -4282, -4829, -5440, -5714, -5739, -5068, -3934, -2727, -1535, -778, 125, 794, 1113, 1136, 747, 260, -570, -1636, -2791, -3987, -4780, -5150, -4911, -4289, -3479, -2526, -1798, -1163, -673, -363, -251, -557, -1250, -2336, -3343, -3953, -4178, -4111, -4003, -3819, -3411, -2818, -2038, -1189, -204, 573, 970, 853, 115, -916, -1561, -1729, -1746, -2096, -2495, -2657, -2423, -2079, -1730, -1609, -1475, -1247, -1328, -2871, -5501, -7895, -8838, -8196, -6292, -3517, -415, 2577, 5422, 7631, 9380, 10909, 12494, 13801, 13849, 12656, 10805, 8777, 6981, 5340, 3978, 2422, 491, -1554, -3433, -4686, -4934, -3706, -1282, 1167, 3131, 4432, 5372, 6181, 7178, 8381, 9089, 9026, 8393, 7416, 6225, 4865, 3594, 2118, 121, -2231, -4615, -6465, -7369, -7073, -5672, -3816, -2033, -462, 737, 1708, 2434, 3087, 3527, 3547, 3122, 2193, 840, -702, -2201, -3269, -3981, -4639, -5349, -5956, -6006, -5254, -3659, -1636, 119, 1422, 2099, 2325, 1985, 1277, 581, -252, -1073, -2095, -3246, -4363, -5212, -5347, -4905, -3950, -2833, -1934, -1367, -969, -623, -352, -255, -334, -751, -1573, -2577, -3422, -4085, -4415, -4457, -4105, -3620, -2998, -2180, -1480, -817, -234, 312, 656, 336, -96, -619, -1020, -1524, -2176, -2477, -2754, -2509, -2233, -1930, -1460, -967, -268, -953, -3507, -6925, -9845, -10784, -9850, -7109, -3521, -167, 3015, 5315, 7291, 9120, 11326, 13939, 15491, 15483, 13808, 11456, 9169, 7271, 6083, 4862, 2944, 322, -2754, -5403, -7041, -6803, -4529, -1542, 1152, 2985, 4188, 5121, 6281, 7955, 9568, 10452, 10644, 10116, 8815, 6980, 5032, 3328, 1382, -827, -3145, -5415, -7023, -7568, -6840, -5183, -3371, -1669, -427, 258, 697, 1202, 2037, 2776, 3309, 3584, 3270, 2306, 754, -973, -2719, -4262, -5246, -5765, -5907, -5638, -4880, -3872, -2885, -1865, -900, -56, 637, 1065, 1170, 922, 215, -854, -2106, -3170, -3926, -4303, -4451, -4575, -4451, -3925, -3012, -1990, -961, -109, 379, 252, -277, -996, -1644, -2027, -2138, -2191, -2580, -3145, -3535, -3843, -3613, -3239, -2728, -2081, -1335, -143, 852, 1359, 1254, 804, 790, 289, -434, -1316, -1911, -1514, -1291, -987, -1008, -1080, -552, -1256, -3587, -7447, -10543, -11311, -10378, -7643, -4339, -722, 2922, 5450, 7429, 8830, 10947, 13884, 16009, 16389, 14444, 11755, 9078, 6770, 5293, 4039, 2625, 389, -2619, -5640, -7975, -8349, -6483, -3398, -307, 1992, 3553, 4536, 5447, 6846, 8399, 9666, 10196, 9920, 8786, 6905, 5011, 3580, 2334, 888, -1004, -3060, -5028, -6304, -6511, -5912, -4788, -3510, -2401, -1716, -1362, -627, 652, 2115, 3287, 3842, 3750, 2956, 1699, 451, -911, -1959, -2748, -3526, -4209, -4947, -5230, -5082, -4623, -3726, -2687, -1379, -385, 255, 573, 425, 231, -332, -1038, -1555, -2002, -2124, -2392, -2634, -2640, -2447, -1891, -1501, -1158, -940, -945, -1108, -1551, -1910, -1984, -1905, -1639, -1487, -1594, -1972, -2512, -2851, -2917, -2561, -1969, -1563, -1272, -927, -389, 75, 80, -69, -96, -6, -48, -387, -803, -1056, -819, -330, -8, -42, -411, -917, -2466, -5332, -8478, -10415, -10357, -8540, -5710, -2536, 320, 2886, 4739, 6047, 7346, 9137, 11555, 13270, 13613, 12666, 10992, 9169, 7432, 6103, 4727, 2948, 621, -2162, -4706, -6458, -6603, -5086, -2750, -408, 1121, 1809, 1859, 2088, 3177, 4911, 6764, 8261, 9093, 8873, 7807, 6596, 5591, 4565, 3258, 1463, -637, -2688, -4210, -4872, -4851, -4486, -3900, -3527, -3525, -3423, -2702, -1457, -180, 1011, 2197, 3125, 3384, 2986, 2300, 1434, 311, -830, -1931, -2841, -3110, -3126, -3098, -3273, -3487, -3364, -3271, -3145, -2788, -2357, -1863, -1857, -2107, -2337, -2238, -1568, -776, 38, 233, 34, -373, -1155, -1726, -2093, -2069, -1917, -2106, -2303, -2615, -2748, -2655, -2457, -2036, -1935, -1881, -1878, -2020, -1915, -1666, -1212, -1013, -1124, -1093, -959, -622, -245, 8, 236, 281, 113, -214, -481, -198, 528, 1218, 1283, 557, -440, -1620, -3501, -6177, -8789, -10054, -9566, -7824, -5513, -3191, -989, 902, 2310, 3723, 5549, 8208, 11241, 13241, 13638, 12715, 11325, 9839, 8509, 7695, 6767, 5206, 2760, -201, -2870, -4747, -5087, -4147, -2918, -2092, -1961, -2109, -2131, -1379, 496, 3044, 5618, 7704, 8894, 8945, 8219, 7433, 6848, 6217, 5163, 3633, 1880, 165, -1198, -2048, -2520, -2974, -3526, -4267, -5198, -5594, -5145, -3991, -2627, -1376, -205, 562, 1016, 1294, 1504, 1517, 1146, 527, -182, -597, -733, -910, -1279, -1863, -2563, -3330, -4038, -4347, -3948, -3152, -2501, -2315, -2515, -2603, -2353, -1702, -847, -390, -321, -722, -1491, -2125, -2379, -2039, -1456, -944, -746, -1033, -1351, -1562, -1559, -1405, -1386, -1426, -1689, -2136, -2479, -2554, -2237, -1880, -1730, -1767, -1892, -1857, -1531, -812, 232, 1215, 1832, 2003, 1736, 1262, 856, 729, 720, 657, 563, 273, -229, -934, -2068, -3925, -6196, -7770, -8095, -7279, -5845, -4236, -2782, -1654, -740, 439, 2402, 5271, 8796, 11646, 12891, 12649, 11707, 10574, 9691, 9332, 9318, 8784, 7059, 4336, 1150, -1564, -3257, -3711, -3592, -3559, -3689, -3927, -4046, -3734, -2617, -729, 1343, 3075, 4345, 4957, 5200, 5511, 6038, 6559, 6764, 6445, 5648, 4493, 3293, 2198, 1066, -28, -1115, -2162, -3339, -4341, -4702, -4602, -4242, -3864, -3551, -3371, -3351, -3193, -2888, -2364, -1515, -567, 291, 871, 1292, 1386, 1081, 587, 50, -355, -680, -854, -867, -1055, -1565, -2299, -3229, -4084, -4636, -4689, -4322, -3737, -3180, -2830, -2690, -2550, -2094, -1296, -297, 668, 1415, 1690, 1375, 642, -120, -700, -1084, -1328, -1457, -1738, -2029, -2188, -2140, -1948, -1817, -1761, -1764, -1609, -1210, -481, 307, 935, 1203, 1144, 748, 373, 209, 323, 729, 1106, 1350, 1175, 890, 668, 538, -298, -2106, -4419, -6369, -7344, -7131, -5881, -4197, -2506, -1421, -896, -483, 622, 2663, 5518, 8134, 9843, 10302, 9857, 9186, 8784, 8997, 9204, 8912, 7580, 5316, 2475, 47, -1327, -1526, -1166, -1063, -1526, -2532, -3613, -4376, -4202, -3194, -1728, -246, 1017, 1916, 2584, 3323, 4212, 5107, 5721, 6028, 6055, 5807, 5363, 4854, 4296, 3534, 2488, 1134, -231, -1381, -2074, -2469, -2850, -3400, -4152, -4927, -5539, -5604, -5107, -4266, -3568, -3072, -2756, -2381, -1742, -814, 234, 949, 1213, 1032, 831, 830, 1174, 1504, 1281, 239, -1305, -2750, -3639, -3606, -2836, -1944, -1732, -2331, -3496, -4656, -5071, -4377, -2831, -1392, -613, -570, -1007, -1538, -1763, -1447, -782, -87, 381, 494, 252, 89, 164, 344, 353, 126, -124, -290, -235, -55, -21, -452, -1215, -1952, -2355, -2269, -1665, -668, 340, 1027, 1129, 894, 630, 647, 737, 191, -1317, -3250, -4764, -5354, -4972, -4127, -3178, -2559, -2346, -2267, -1739, -346, 1793, 4323, 6336, 7304, 7201, 6663, 6369, 6746, 7592, 8403, 8599, 8016, 6756, 5069, 3568, 2527, 2111, 1858, 1342, 428, -687, -1708, -2407, -2568, -2341, -1865, -1351, -920, -657, -387, 35, 688, 1425, 2098, 2808, 3528, 4122, 4549, 4801, 4865, 4678, 4104, 3345, 2694, 2311, 2011, 1604, 877, -247, -1609, -3019, -4063, -4572, -4696, -4745, -4871, -5093, -5311, -5346, -5232, -4877, -4375, -3763, -3238, -2639, -1977, -1148, -285, 323, 606, 587, 499, 426, 599, 920, 1359, 1444, 870, -210, -1538, -2604, -3179, -3127, -2715, -2448, -2617, -3299, -4158, -4672, -4476, -3558, -2393, -1318, -632, -398, -395, -430, -84, 513, 1106, 1389, 1255, 931, 593, 415, 225, 96, -280, -607, -790, -582, 45, 695, 1104, 1077, 861, 423, 234, 285, 639, 698, 80, -1641, -3685, -5143, -5462, -4693, -3763, -3004, -2824, -2939, -3187, -2603, -1080, 1229, 3461, 4974, 5322, 4883, 4397, 4534, 5603, 7142, 8483, 8823, 8071, 6706, 5433, 4635, 4460, 4600, 4573, 4002, 2774, 1319, 68, -696, -1034, -1189, -1407, -1650, -1786, -1837, -1720, -1482, -1267, -1091, -974, -570, 216, 1209, 2243, 2996, 3437, 3542, 3406, 3149, 3081, 3209, 3262, 3113, 2624, 1827, 843, -177, -1027, -1649, -2126, -2680, -3351, -4222, -5001, -5689, -6221, -6602, -6695, -6437, -5859, -4972, -3976, -2974, -2333, -2051, -1926, -1664, -942, 183, 1459, 2389, 2687, 2244, 1279, 286, -289, -202, 183, 386, 11, -962, -2284, -3504, -4242, -4233, -3654, -2870, -2149, -1792, -1802, -1963, -2074, -2028, -1640, -1027, -367, 33, 134, -32, -215, -229, 54, 676, 1352, 1868, 2107, 2058, 1824, 1481, 1210, 1026, 997, 1029, 1212, 1316, 1290, 921, 29, -1443, -3112, -4290, -4581, -4004, -3282, -2855, -3040, -3604, -4278, -4147, -3093, -1198, 774, 2117, 2475, 2278, 2137, 2765, 4384, 6471, 8278, 9019, 8548, 7433, 6331, 5709, 5759, 6110, 6403, 6165, 5243, 3926, 2611, 1483, 696, 123, -322, -841, -1411, -2150, -2885, -3522, -3937, -4013, -3693, -2940, -1902, -942, -423, -234, -142, 127, 722, 1676, 2890, 3963, 4583, 4554, 3951, 3122, 2302, 1697, 1394, 1246, 973, 285, -824, -2213, -3644, -4801, -5600, -5918, -5887, -5700, -5658, -5653, -5559, -5214, -4664, -4059, -3373, -2727, -2192, -1795, -1385, -911, -411, 49, 418, 725, 931, 1081, 1127, 1058, 858, 509, 174, -39, -37, 4, -112, -542, -1158, -1900, -2535, -2847, -2838, -2606, -2381, -2235, -2268, -2296, -2195, -1827, -1234, -546, 138, 652, 886, 976, 968, 985, 1006, 998, 1090, 1257, 1467, 1619, 1582, 1364, 1159, 1096, 1301, 1758, 2330, 2708, 2681, 2121, 1187, 175, -646, -1177, -1440, -1717, -2043, -2509, -3217, -3914, -4289, -4225, -3639, -2741, -1861, -1135, -708, -348, 242, 1265, 2649, 4280, 5683, 6549, 6788, 6641, 6625, 6936, 7437, 7836, 7849, 7298, 6289, 5030, 3887, 3178, 2816, 2425, 1811, 838, -342, -1416, -2350, -3115, -3646, -3827, -3762, -3455, -2999, -2629, -2449, -2583, -2713, -2423, -1581, -384, 861, 1632, 1822, 1614, 1232, 1082, 1249, 1555, 1755, 1652, 1251, 792, 238, -429, -1126, -1760, -2407, -2918, -3323, -3554, -3780, -4211, -4691, -5016, -4973, -4454, -3567, -2752, -2291, -2342, -2535, -2588, -2195, -1343, -449, 188, 399, 241, 11, -70, 139, 533, 961, 1217, 1205, 1070, 920, 809, 844, 964, 1089, 1040, 715, 178, -415, -936, -1219, -1388, -1469, -1502, -1616, -1922, -2249, -2444, -2491, -2246, -1811, -1199, -452, 26, 130, -96, -950, -1919, -2393, -2241, -1648, -1166, -1438, -2064, -2746, -3140, -2628, -1374, 17, 1149, 1466, 1045, 700, 730, 1588, 3197, 4720, 5608, 5716, 5107, 4587, 4600, 5054, 6041, 7087, 7480, 7161, 6353, 5346, 4727, 4365, 4192, 4027, 3692, 2955, 2056, 1024, 137, -365, -580, -566, -434, -419, -748, -1220, -1727, -1973, -1800, -1284, -616, -37, 75, -192, -576, -848, -672, -31, 672, 1130, 1165, 599, -153, -780, -1150, -1111, -901, -873, -1034, -1500, -2196, -2885, -3512, -3933, -4035, -3882, -3667, -3466, -3364, -3294, -3234, -3208, -3009, -2532, -1852, -1107, -633, -548, -695, -914, -1017, -752, -218, 403, 749, 638, 273, -117, -334, -227, 222, 695, 899, 822, 522, 158, -72, -189, -136, -83, -203, -607, -1075, -1438, -1596, -1521, -1438, -1376, -1330, -1372, -1469, -1329, -1003, -410, 218, 713, 1049, 1201, 1015, 739, 599, 756, 1287, 1825, 2036, 1885, 1098, -296, -1505, -2000, -1550, -733, -546, -1275, -2478, -3783, -4469, -3979, -2689, -1246, -547, -889, -1650, -1890, -1271, 424, 2630, 4408, 5255, 5163, 4654, 4576, 5094, 6131, 7434, 8317, 8341, 7490, 6204, 5075, 4669, 4844, 5213, 5342, 4829, 3596, 2000, 491, -361, -582, -472, -310, -431, -1041, -1975, -2858, -3380, -3289, -2865, -2429, -2105, -2002, -2190, -2375, -2298, -1919, -1162, -426, -17, 121, 77, 10, 172, 398, 642, 777, 599, 255, -127, -660, -1131, -1429, -1654, -1649, -1649, -1951, -2362, -2877, -3617, -4142, -4257, -4018, -3450, -3021, -2975, -3254, -3773, -4023, -3676, -2897, -1822, -878, -503, -516, -521, -247, 503, 1523, 2401, 2871, 2751, 2128, 1489, 1143, 1169, 1491, 1626, 1312, 739, -15, -641, -814, -685, -350, -57, -235, -685, -1097, -1394, -1419, -1144, -791, -451, -468, -816, -1101, -1155, -814, -8, 647, 803, 280, -1019, -2132, -2204, -1505, -542, -144, -815, -1955, -3013, -3255, -2138, -425, 932, 1401, 896, 188, 28, 657, 2099, 3800, 4762, 4752, 4076, 3336, 3320, 4027, 5043, 6110, 6582, 6171, 5201, 4193, 3728, 3953, 4361, 4563, 4418, 3733, 2673, 1694, 1067, 917, 1190, 1456, 1396, 975, 142, -828, -1541, -1736, -1473, -1120, -1038, -1230, -1652, -2232, -2711, -2809, -2500, -2044, -1674, -1530, -1624, -1767, -1801, -1576, -996, -532, -531, -820, -1214, -1392, -1168, -920, -714, -644, -1029, -1503, -1741, -1864, -1832, -1940, -2336, -2671, -2921, -3038, -2943, -2793, -2619, -2411, -2190, -1763, -1193, -687, -330, -197, -236, -342, -395, -277, 64, 430, 630, 607, 446, 176, -19, -18, 142, 307, 324, 122, -168, -348, -404, -403, -427, -563, -638, -606, -546, -536, -547, -662, -816, -830, -584, -171, 155, 119, -157, -398, -351, 115, 738, 1136, 1189, 586, -464, -1072, -1026, -475, -1, -444, -1414, -2388, -2944, -2518, -1359, -436, -175, -686, -1480, -1475, -552, 910, 2651, 3842, 3978, 3400, 2713, 2725, 3667, 4929, 5991, 6513, 6145, 5139, 4142, 3744, 4192, 4989, 5413, 5335, 4748, 3769, 2859, 2199, 1887, 1914, 1820, 1436, 814, -103, -1114, -1968, -2448, -2447, -2251, -2200, -2437, -3053, -3672, -3836, -3431, -2527, -1573, -1078, -1180, -1636, -1982, -1732, -971, -67, 638, 661, 37, -645, -918, -673, -81, 271, 87, -572, -1531, -2276, -2460, -2181, -1729, -1581, -1949, -2600, -3118, -3303, -3029, -2478, -2110, -2015, -2164, -2351, -2256, -1852, -1373, -920, -709, -787, -768, -532, -93, 528, 1064, 1338, 1363, 1238, 1121, 1112, 1087, 1049, 934, 777, 601, 378, 149, -21, -138, -252, -287, -251, -323, -468, -621, -672, -633, -595, -565, -454, -326, -234, -179, -179, -116, -17, -16, -93, -493, -1160, -1554, -1426, -870, -364, -722, -1590, -2331, -2692, -2081, -801, 199, 547, 109, -636, -622, 237, 1413, 2739, 3418, 3267, 2719, 2134, 2175, 3067, 4214, 5118, 5601, 5376, 4673, 4147, 4143, 4862, 5781, 6145, 5826, 5007, 3939, 3075, 2710, 2728, 2815, 2608, 1879, 953, 63, -745, -1209, -1422, -1541, -1617, -1888, -2339, -2729, -2994, -3129, -3026, -2772, -2532, -2406, -2463, -2562, -2599, -2543, -2373, -2076, -1644, -1327, -1207, -1267, -1361, -1270, -1025, -627, -242, -84, -157, -452, -662, -691, -648, -681, -912, -1205, -1531, -1786, -1847, -1785, -1721, -1820, -2021, -2134, -2012, -1821, -1583, -1251, -993, -693, -551, -542, -516, -528, -542, -468, -255, -71, 17, -117, -294, -353, -447, -451, -310, -89, 189, 431, 476, 471, 461, 359, 338, 397, 485, 664, 727, 592, 455, 185, -114, -183, -175, -79, 72, 25, -180, -521, -1093, -1491, -1438, -1135, -803, -992, -1698, -2280, -2452, -2001, -1088, -311, -71, -312, -745, -725, -7, 969, 1976, 2630, 2742, 2621, 2578, 2864, 3542, 4320, 4858, 5201, 5302, 5241, 5144, 5125, 5287, 5422, 5387, 5045, 4483, 3843, 3210, 2767, 2514, 2305, 2016, 1507, 816, 199, -247, -517, -653, -781, -912, -1201, -1653, -2084, -2363, -2396, -2251, -2078, -2041, -2159, -2478, -2711, -2627, -2320, -1837, -1568, -1661, -1865, -1955, -1778, -1279, -792, -624, -738, -1200, -1473, -1393, -1140, -755, -613, -748, -1040, -1355, -1482, -1302, -990, -714, -581, -733, -924, -994, -934, -731, -489, -331, -418, -694, -973, -1093, -1058, -920, -803, -836, -984, -1196, -1297, -1211, -974, -643, -331, -188, -204, -278, -321, -159, 157, 512, 728, 688, 522, 319, 218, 202, 203, 148, 10, -154, -238, -206, -183, -219, -303, -334, -289, -289, -359, -500, -784, -1055, -1014, -791, -604, -856, -1505, -2042, -2212, -1811, -1047, -429, -314, -604, -918, -656, 282, 1359, 2223, 2574, 2491, 2479, 2777, 3439, 4219, 4713, 4839, 4782, 4705, 4668, 4693, 4734, 4745, 4646, 4498, 4318, 4057, 3750, 3371, 3077, 2853, 2673, 2494, 2102, 1557, 978, 486, 184, 54, -130, -446, -905, -1469, -1895, -2088, -2058, -2007, -2098, -2359, -2606, -2723, -2644, -2421, -2257, -2224, -2363, -2526, -2487, -2275, -1943, -1772, -1813, -1958, -2127, -2092, -1812, -1425, -1152, -1124, -1265, -1289, -1009, -620, -247, -64, -82, -181, -286, -285, -146, 22, 24, -186, -519, -813, -993, -1052, -1009, -1002, -1039, -1158, -1285, -1313, -1273, -1183, -1080, -1012, -928, -850, -821, -779, -666, -546, -356, -163, -17, 119, 128, 46, 82, 202, 357, 467, 437, 404, 342, 218, 199, 253, 366, 497, 604, 632, 507, 335, 243, 307, 420, 537, 543, 353, 82, -191, -250, -72, 133, 263, 236, 118, 61, 147, 393, 724, 1045, 1250, 1300, 1181, 1055, 1074, 1288, 1648, 1964, 2047, 1898, 1688, 1621, 1812, 2175, 2446, 2553, 2495, 2345, 2301, 2374, 2491, 2513, 2393, 2152, 1952, 1862, 1793, 1710, 1587, 1369, 1130, 935, 835, 807, 696, 503, 324, 152, 2, -128, -238, -377, -529, -667, -794, -955, -1166, -1362, -1566, -1764, -1912, -2049, -2137, -2189, -2242, -2288, -2374, -2444, -2446, -2350, -2200, -2032, -1892, -1815, -1800, -1863, -1866, -1769, -1563, -1400, -1337, -1349, -1401, -1358, -1205, -1009, -843, -810, -834, -833, -738, -540, -356, -240, -216, -222, -246, -228, -96, 62, 237, 291, 269, 207, 148, 209, 355, 515, 590, 538, 415, 295, 281, 365, 431, 446, 395, 289, 226, 244, 315, 396, 413, 373, 319, 255, 234, 255, 319, 351, 354, 305, 259, 249, 251, 278, 265, 289, 337, 391, 421, 385, 314, 233, 172, 179, 244, 246, 244, 216, 224, 275, 282, 351, 384, 387, 410, 486, 659, 789, 859, 876, 816, 753, 724, 810, 973, 1158, 1255, 1268, 1166, 1045, 1056, 1182, 1346, 1447, 1495, 1447, 1335, 1198, 1102, 1086, 1071, 1056, 1026, 923, 768, 577, 416, 267, 208, 200, 122, 13, -139, -289, -411, -506, -533, -528, -564, -611, -648, -655, -661, -669, -687, -660, -620, -604, -598, -615, -689, -757, -811, -866, -888, -942, -986, -1024, -1097, -1195, -1293, -1387, -1456, -1467, -1484, -1495, -1521, -1525, -1546, -1535, -1507, -1502, -1467, -1387, -1258, -1139, -1054, -985, -940, -894, -859, -767, -606, -442, -294, -219, -236, -268, -232, -104, 67, 223, 305, 297, 238, 196, 192, 210, 265, 307, 330, 320, 299, 307, 360, 427, 479, 498, 515, 544, 571, 623, 633, 592, 550, 463, 415, 444, 489, 506, 511, 472, 449, 425, 392, 432, 517, 636, 708, 731, 686, 647, 661, 739, 823, 874, 896, 881, 900, 953, 1031, 1119, 1185, 1209, 1235, 1258, 1295, 1386, 1459, 1498, 1465, 1426, 1420, 1378, 1354, 1287, 1190, 1101, 978, 894, 787, 659, 521, 359, 210, 58, -73, -196, -327, -450, -566, -641, -731, -826, -875, -941, -958, -926, -924, -926, -914, -915, -888, -859, -788, -672, -523, -443, -451, -504, -610, -640, -578, -451, -301, -244, -344, -508, -636, -666, -582, -466, -429, -503, -721, -948, -1055, -1011, -904, -814, -804, -912, -1017, -1101, -1071, -973, -845, -734, -697, -692, -719, -691, -670, -632, -565, -534, -510, -489, -496, -492, -493, -523, -486, -408, -309, -231, -215, -225, -273, -288, -237, -113, -2, 53, 53, 34, 11, 27, 118, 205, 289, 344, 377, 367, 353, 356, 391, 456, 498, 526, 521, 532, 586, 670, 736, 760, 725, 705, 692, 731, 817, 873, 911, 876, 825, 825, 874, 939, 1018, 1099, 1126, 1112, 1103, 1118, 1115, 1164, 1251, 1341, 1346, 1293, 1226, 1124, 1045, 966, 945, 921, 869, 782, 653, 501, 360, 265, 208, 130, 11, -86, -219, -348, -456, -544, -581, -641, -692, -719, -745, -787, -874, -931, -968, -995, -957, -906, -841, -774, -753, -777, -787, -754, -646, -513, -418, -389, -401, -449, -532, -568, -515, -467, -422, -439, -497, -603, -713, -716, -675, -603, -575, -552, -578, -613, -616, -587, -536, -494, -446, -425, -414, -449, -435, -408, -385, -356, -318, -298, -309, -304, -290, -266, -231, -208, -179, -153, -154, -112, -48, 31, 98, 149, 185, 192, 213, 260, 338, 395, 430, 455, 435, 419, 412, 396, 394, 394, 401, 393, 364, 305, 299, 288, 319, 346, 357, 360, 332, 349, 384, 461, 511, 530, 540, 526, 512, 513, 550, 604, 625, 648, 653, 628, 613, 645, 690, 707, 698, 643, 603, 563, 576, 613, 646, 635, 575, 534, 483, 443, 414, 388, 346, 273, 217, 128, 81, 54, 29, -16, -93, -184, -327, -435, -490, -503, -493, -490, -524, -574, -621, -650, -592, -505, -415, -365, -347, -327, -328, -314, -284, -260, -225, -209, -248, -310, -365, -389, -392, -357, -348, -356, -379, -424, -442, -429, -396, -391, -403, -432, -456, -462, -420, -366, -340, -287, -281, -292, -313, -318, -278, -218, -155, -135, -146, -177, -185, -182, -155, -145, -132, -161, -201, -210, -200, -145, -85, -44, -35, -55, -73, -43, -38, -6, 43, 57, 60, 44, 15, -21, -14, -4, 17, 44, 50, 27, -1, -22, -15, 14, 35, 57, 59, 61, 81, 84, 83, 90, 110, 147, 187, 218, 238, 245, 272, 300, 312, 310, 311, 334, 374, 375, 386, 395, 399, 402, 406, 414, 455, 491, 489, 502, 498, 518, 537, 559, 572, 581, 544, 481, 429, 356, 313, 252, 188, 146, 107, 50, -15, -75, -133, -183, -221, -235, -257, -269, -280, -305, -318, -344, -338, -306, -276, -254, -269, -281, -266, -248, -215, -173, -161, -148, -133, -137, -132, -113, -94, -110, -125, -131, -132, -151, -168, -151, -121, -99, -105, -109, -102, -102, -102, -63, -37, -63, -100, -102, -101, -129, -148, -125, -123, -106, -92, -81, -98, -118, -86, -48, -3, 33, 33, 31, 49, 47, 66, 81, 67, 60, 66, 54, -7, -50, -78, -108, -115, -132, -157, -176, -207, -210, -232, -245, -264, -299, -297, -273, -265, -245, -193, -168, -122, -120, -119, -84, -36, 12, 39, 100, 145, 176, 174, 184, 185, 182, 209, 215, 237, 252, 268, 264, 246, 268, 306, 336, 339, 335, 324, 318, 308, 310, 313, 330, 346, 342, 319, 232, 173, 168, 178, 157, 113, 59, 41, 19, -31, -44, -55, -60, -83, -99, -105, -109, -101, -96, -80, -78, -74, -71, -66, -32, 5, 14, 43, 48, 32, 31, 42, 39, 30, 12, -38, -49, -19, 13, 15, 5, -5, -22, -29, -20, 3, 14, 31, 43, 25, -5, -44, -60, -69, -69, -78, -95, -126, -159, -177, -189, -202, -185, -166, -180, -176, -166, -134, -109, -112, -134, -139, -148, -145, -116, -106, -96, -96, -83, -58, -50, -54, -50, -54, -41, -14, 8, 8, -19, -22, -27, -35, -41, -61, -56, -41, -26, -4, -18, -27, 6, 4, 8, 25, 14, 27, 24, 27, 34, 13, 10, -16, 3, 16, -10, -18, -24, -36, -55, -90, -95, -72, -81, -55, -44, -41, -17, 17, 42, 49, 47, 75, 112, 131, 149, 176, 186, 155, 144, 138, 133, 153, 155, 174, 199, 181, 180, 164, 133, 129, 162, 190, 179, 160, 163, 191, 188, 169, 152, 127, 128, 130, 135, 111, 104, 93, 97, 106, 91, 90, 92, 98, 82, 36, -13, -43, -43, -37, -44, -64, -86, -125, -165, -180, -198, -224, -233, -229, -241, -234, -232, -232, -227, -207, -197, -197, -204, -197, -176, -138, -86, -87, -82, -53, -44, -27, -11, -3, 5, 24, 46, 38, 20, 14, 19, 33, 44, 21, 0, -19, -54, -72, -72, -72, -80, -74, -42, -54, -64, -74, -73, -63, -73, -94, -110, -105, -102, -70, -47, -20, -19, -26, -37, -71, -79, -70, -39, -16, 11, 0, -49, -66, -76, -69, -41, -2, 6, 19, 23, 8, 27, 40, 83, 107, 104, 107, 81, 62, 71, 71, 61, 60, 59, 34, 2, -1, 13, 55, 80, 52, 27, 31, 68, 84, 95, 120, 146, 129, 107, 91, 73, 50, 76, 105, 90, 53, 16, 9, 30, 67, 88, 90, 87, 91, 88, 65, 74, 61, 82, 112, 122, 95, 53, 50, 50, 32, 2, -11, 3, 12, 34, 51, 53, 16, -9, -43, -62, -55, -50, -54, -62, -45, -22, -24, -43, -65, -66, -54, -37, -27, -32, -12, -5, -29, -66, -71, -50, -41, -41, -38, -44, -70, -54, -63, -67, -49, -44, -50, -55, -80, -87, -67, -73, -92, -124, -121, -126, -124, -108, -89, -62, -68, -80, -101, -101, -70, -27, 2, -8, -15, -50, -58, -86, -103, -121, -107, -71, -80, -66, -54, -11, -5, 5, -15, -54, -45, -25, -8, -17, -3, 12, -8, -28, -49, -38, -28, -30, -1, 6, -25, -41, -20, -5, 0, 38, 77, 114, 122, 92, 52, 45, 76, 65, 65, 84, 83, 66, 38, 50, 37, 26, 31, 81, 94, 86, 96, 100, 101, 93, 118, 89, 63, 64, 64, 81, 98, 111, 101, 81, 80, 50, 40, 56, 61, 52, 63, 65, 78, 39, 15, 31, 23, 20, -7, -15, -34, -37, -34, -37, -37, -25, 34, 60, 22, -35, -27, -8, 11, 0, -13, 1, -15, -44, -67, -63, -46, -64, -94, -88, -58, -82, -80, -55, -49, -65, -88, -132, -136, -102, -110, -75, -90, -90, -53, -44, -54, -84, -82, -59, -46, -46, -55, -84, -71, -30, -37, -64, -85, -90, -90, -57, -24, -19, -27, -44, -42, -22, -19, -10, -8, -17, -7, -10, -33, -42, -31, -25, -33, -22, -13, -9, -2, 20, -4, -16, 1, 23, 25, 25, 56, 45, 33, 44, 39, 37, 42, 32, 29, 36, 30, 53, 40, 50, 39, 21, 38, 72, 77, 42, 31, 39, 61, 57, 24, 6, 40, 49, 35, 40, 27, 30, 26, 26, 28, 24, 31, 36, 50, 30, 17, 13, 29, 49, 28, 38, 37, 47, 53, 35, 46, 8, -50, -76, -25, -3, -35, -27, -23, -25, -16, -12, 1, -12, -12, 19, 18, -4, -52, -36, 2, 13, 2, -32, -44, -38, -54, -58, -43, -43, -45, -43, -43, -68, -89, -60, -9, 7, -8, -18, -20, -30, -42, -49, -33, -41, -53, -45, -27, -8, -6, -5, -19, -7, 3, -6, -14, -27, -26, -21, -17, -32, -16, 7, 3, -7, -33, -27, -3, 29, 29, 8, 3, 13, 3, -9, -9, -10, -24, -6, 12, 38, 27, 2, -1, 5, 9, -12, -15, -12, -4, 3, 14, 35, 24, 16, 25, 45, 28, 5, 21, 28, 47, 69, 37, 33, 36, 26, 16, 2, 4, 9, 0, 40, 55, 26, 20, 47, 65, 55, 36, 21, 33, 44, 60, 62, 45, 36, 32, 20, 6, -8, -15, 3, 18, -4, -15, -14, -26, -6, 8, 12, -10, -20, 0, 7, 14, -8, -14, 5, 9, 6, -20, -46, -45, -38, -30, -18, -19, -14, -24, -26, -21, -26, -17, -15, -9, -10, -39, -45, -22, 8, 6, -24, -45, -57, -22, 15, 13, -2, -16, -34, -38, -22, -14, -21, -26, -29, -38, -39, -24, -10, -18, -20, -25, -27, -17, -2, -31, -20, -25, -54, -32, -23, -9, -19, -35, -32, -26, -15, -13, -16, -11, 4, 10, -2, -6, -27, -37, 1, 34, 20, 2, -16, -15, -7, -10, -9, 6, 22, 13, 14, 36, 31, 35, 33, 24, 13, -2, -6, 5, 3, 10, 15, 15, 48, 51, 39, 28, 17, 18, 7, 22, 46, 49, 39, 24, 50, 48, 23, 35, 51, 57, 56, 51, 38, 29, 46, 66, 67, 51, 32, 47, 50, 47, 43, 37, 34, 29, 25, 10, -10, -18, 5, 14, 1, -8, 2, 6, 6, 19, -1, 10, 6, -40, -41, -20, -35, -42, -32, -24, -34, -29, -26, -50, -62, -58, -68, -83, -52, -33, -16, -6, -19, -36, -48, -51, -52, -42, -49, -43, -33, -7, 3, -26, -15, -3, -17, -27, -21, -8, -32, -39, -38, -26, -9, -21, -31, -31, -32, -52, -39, -16, 9, 26, 18, 1, -21, -21, -18, -19, 5, 3, -16, -17, -4, 15, 6, 6, -9, -15, 0, -14, -27, -22, 3, 16, 12, 1, 7, 11, 7, 10, 1, 2, 11, 13, 17, 15, 14, 11, 16, 27, 36, 34, 30, 14, 6, 21, 34, 29, 33, 34, 32, 51, 54, 48, 42, 31, 43, 46, 32, 33, 35, 37, 41, 50, 40, 50, 40, 27, 18, 6, 27, 43, 54, 27, 8, -10, -1, 12, 10, 60, 75, 44, 27, -10, 2, 22, 20, 6, -12, 2, -19, -21, 7, 16, 1, -5, -11, -22, -7, -19, -32, -26, -31, -3, -2, -6, -16, -25, -22, -41, -33, -24, 8, 2, -18, -28, -48, -40, -42, -36, -54, -45, -20, -33, -41, -35, -38, -27, -30, -53, -45, -46, -35, -20, -30, -14, -21, -34, -19, -13, -21, -47, -29, -2, 10, 2, -15, -18, -20, -10, 2, 7, 2, 4, -1, 15, 20, 0, 26, 25, 37, 60, 43, 27, 34, 57, 79, 64, 60, 53, 32, 40, 36, 29, 21, 39, 66, 56, 58, 45, 45, 51, 43, 40, 33, 25, 18, 25, 37, 32, 22, 34, 28, 8, 2, -17, -11, 1, 4, -5, 9, 16, 20, 22, 1, -7, -15, -18, -35, -35, -32, -32, -26, -21, -3, -16, -16, -20, -21, -15, -18, 0, -5, -11, -5, -13, -18, -21, -1, -11, -38, -16, -23, -28, -24, -22, -12, -15, -26, -28, -19, -18, -22, -21, -27, -15, -4, -19, -15, 0, -11, -19, -10, -7, 14, 0, 4, 32, 6, 16, 11, 0, 3, -13, -26, -10, -13, -23, -24, -31, -41, -32, -21, -25, -6, -4, -36, -16, -2, -3, 2, -20, -6, -8, -13, -6, -11, -1, 6, 3, 2, -1, -19, -11, -3, -22, -16, 3, 1, 0, 8, 17, 22, 20, 4, 17, 22, -8, 3, 11, 20, 41, 32, 20, 26, 40, 23, 26, 23, 12, 15, -14, -12, -15, -18, -13, -18, -5, -6, -12, -15, 7, 3, 12, 22, 16, 15, 14, 28, 19, 6, 9, 11, 16, -4, 15, 33, 33, 11, -3, 2, 3, -3, -15, 20, 33, 31, 15, 8, 8, 5, -6, -20, -25, -19, -12, -8, -2, 23, 17, 17, 29, 24, 3, -7, -21, -33, -18, 2, -3, -5, -10, -20, -6, -4, -2, -1, 11, 20, -1, -22, -30, 0, 16, 2, -35, -36, -21, -24, -33, -29, -40, -45, -34, -33, -47, -54, -46, -35, -39, -21, -32, -54, -70, -49, -23, -37, -42, -49, -37, -25, -52, -55, -34, -28, -18, -10, -27, -18, -13, -23, -16, -23, 5, 13, 15, 12, 3, -5, 3, 34, 38, 37, 30, 21, 20, 41, 41, 23, 38, 48, 60, 44, 29, 41, 38, 34, 30, 21, 13, 22, 18, 36, 28, 26, 54, 56, 39, 25, 23, 15, 16, 18, 16, 11, -5, 2, 6, -2, -6, -7, 4, 18, 3, -14, -7, 17, 23, -1, 2, -4, -3, -5, -20, -6, -18, -11, 13, 18, 2, -3, -4, 7, 9, -13, -5, -12, -20, -11, -16, -10, -40, -45, -42, -26, -14, -13, -16, -3, 4, -10, -11, -6, -1, -14, -33, -47, -31, -1, -8, -11, -6, -4, -14, -26, -28, -27, -24, -35, -26, -31, -16, -8, -17, -27, -35, -35, -38, -33, -29, -29, -38, -38, -22, -3, -11, -30, -38, -29, -31, -20, -29, -28, -16, -26, -28, -20, -3, 8, 8, 14, 26, 30, 22, 41, 46, 54, 55, 53, 55, 51, 44, 52, 59, 71, 81, 81, 70, 51, 61, 61, 65, 65, 57, 52, 51, 62, 73, 67, 31, 20, 7, -3, -2, -13, 0, 15, 26, 0, -22, -13, -7, -15, -23, -23, -22, -31, -48, -36, -31, -35, -30, -32, -40, -40, -22, -14, -19, -13, -7, -15, -13, -22, -27, -13, 3, 31, 22, 3, -4, -16, -10, -6, -25, -30, -3, -11, -20, -28, -29, -22, -41, -49, -38, -38, -47, -38, -29, -9, -4, -14, -3, -8, -19, -28, -23, -28, -27, -15, -26, -35, -37, -17, 12, 1, -13, -27, -24, -7, -12, -21, -10, -7, -26, -20, -13, -11, 3, -6, -12, -9, -12, -13, 4, 4, 28, 33, 18, 26, 27, 35, 27, 29, 44, 36, 28, 24, 8, 4, 14, 32, 44, 64, 57, 35, 25, 12, 8, 2, 19, 47, 62, 54, 42, 15, -7, 34, 60, 62, 56, 33, 27, 12, -9, 8, 24, 15, 22, -8, -35, -20, -28, -2, 29, 13, -9, -16, -25, -24, -4, -5, 20, 57, 64, 17, -37, -18, -2, 32, 53, 74, 81, 38, -1, -15, -7, 4, 21, 60, 60, 29, -12, -41, -31, -18, -52, -77, -66, -47, -52, -136, -237, -207, -23, 147, 141, -11, -90, 40, 233, 282, 134, -45, -70, 70, 148, 13, -206, -277, -185, -105, -135, -153, -115, -98, -127, -128, 12, 170, 172, 56, -53, -51, 33, 59, -24, -67, 19, 123, 107, 120, 327, 423, 194, -59, -179, -404, -619, -21, 1141, 355, -3382, -5532, -1582, 4967, 5283, -2348, -7764, -2636, 6959, 8382, 231, -5708, -1765, 5456, 5584, -681, -4097, -1113, 2312, 901, -2289, -1860, 1147, 1415, -1778, -3419, -754, 2609, 2204, -908, -2413, -985, 839, 864, -273, -843, -430, 241, 422, 67, -170, 274, 958, 802, -192, -624, 466, 2032, 1857, -781, -3786, -4041, -560, 3341, 2814, -2049, -5511, -2740, 3376, 5262, 1212, -2371, -478, 3865, 4486, 912, -1515, -75, 1869, 882, -1398, -1310, 813, 862, -2095, -3823, -1799, 1146, 1200, -1187, -2147, -791, -10, -765, -1279, -267, 1195, 1060, -212, -544, 120, 854, 934, 181, -215, 441, 1405, 1820, 882, -765, -1015, -232, 545, 934, 532, -42, -410, -709, -683, -541, -757, -468, 347, 303, -368, -1022, -878, 204, 496, -2, -405, -383, 223, 854, 650, -168, -650, -534, 187, 770, 737, 475, -249, -812, -281, 617, 783, 17, -368, 274, 717, 47, -756, -252, 500, 269, -541, -772, 155, 634, 3, -650, -678, -281, 126, 351, 318, 23, -409, -325, 308, 380, -95, -343, -96, 482, 535, 152, 26, -15, 23, 282, 483, 362, 19, -137, 131, 321, -153, -574, -307, 210, 390, -37, -260, -136, -238, -400, -130, 364, 442, -24, -405, -129, 126, -153, -288, 52, 448, 313, -205, -391, 21, 410, 216, -229, -279, 155, 506, 209, -479, -651, -286, 72, 221, -33, -281, -235, -152, 229, 299, -195, -174, 347, 697, 322, -491, -553, 54, 153, -230, -69, 361, 5, -829, -990, 165, 1034, 310, -467, -140, 492, 408, -449, -656, 175, 624, 38, -595, -345, 327, 332, -505, -728, 63, 570, 409, 71, -49, -129, -387, -376, 72, 326, 5, -323, -332, -217, -47, -214, -209, 250, 464, 316, -151, -1, 823, 620, -510, -710, 497, 1396, 523, -788, -403, 755, 265, -917, -468, 972, 1234, -373, -1279, 92, 1209, 267, -1076, -623, 1116, 1411, -879, -2235, -526, 1656, 1227, -1712, -2643, 206, 2282, 995, -1318, -1461, 774, 1620, 259, -329, 614, 1409, 589, -926, -694, 1053, 1396, -207, -1533, -810, 947, 1059, -654, -1486, -461, 385, -76, -884, -422, 787, 415, -1027, -1348, -169, 1054, 734, -542, -734, 241, 880, 591, -177, -134, 595, 588, -86, -402, 208, 865, 414, -747, -1116, -118, 887, 606, -607, -1276, -524, 489, 386, -355, -574, -226, -53, -304, -266, 286, 390, -286, -598, -80, 499, 442, -87, -346, -30, 338, 402, 116, -62, 233, 571, 134, -649, -474, 499, 815, -188, -1034, -480, 597, 631, -421, -919, -154, 700, 508, -302, -467, 210, 528, -140, -708, -268, 482, 482, -239, -640, -215, 328, 296, -159, -362, 43, 653, 747, 23, -623, -155, 827, 920, 52, -479, 40, 559, -7, -733, -276, 602, 363, -678, -802, 320, 908, -107, -1050, -359, 858, 805, -280, -620, 139, 408, -384, -784, 94, 996, 422, -825, -859, 320, 848, 41, -530, 52, 682, 221, -576, -384, 404, 484, -170, -490, -160, 298, 233, -182, -448, -341, 85, 382, 326, 20, -71, -15, -83, -111, 50, 321, 241, -158, -300, -19, 232, 36, -326, -272, 49, 141, -78, -227, -65, -19, -244, -314, 128, 469, 41, -576, -483, 274, 541, -47, -379, 38, 347, 1, -452, -205, 254, 92, -224, -62, 346, 276, -199, -270, 100, 283, 149, 128, 267, 145, -184, -252, 32, 281, 135, -120, -131, -38, -8, -48, -98, -118, -123, -60, 106, 103, -106, -286, -140, 165, 150, -150, -125, 329, 400, -195, -565, -36, 622, 409, -288, -239, 464, 526, -122, -415, 59, 446, 96, -421, -252, 268, 238, -311, -656, -354, 194, 364, 12, -319, -220, 108, 275, 120, -31, 21, 174, 127, -26, 7, 193, 224, -53, -219, -50, 224, 155, -219, -248, 190, 425, 81, -317, -174, 277, 246, -211, -354, 33, 313, 11, -358, -247, 189, 307, -84, -362, -91, 275, 227, -199, -314, 158, 474, 94, -546, -453, 315, 594, -29, -642, -290, 543, 643, -194, -667, -126, 513, 256, -458, -431, 311, 556, -158, -763, -341, 459, 434, -263, -503, -18, 424, 237, -232, -306, 105, 349, 118, -233, -257, 90, 260, -32, -311, -146, 246, 275, -110, -314, -110, 144, 154, 4, -27, 121, 190, 54, -116, -131, -25, 22, 31, 75, 54, -88, -203, -175, -42, -34, -82, 65, 136, -72, -259, -60, 249, 102, -256, -178, 219, 280, -92, -276, 34, 320, 117, -184, -81, 261, 281, -52, -286, -84, 250, 264, -10, -209, -98, 70, -37, -167, -64, 163, 118, -186, -212, 104, 288, 80, -158, -45, 207, 199, -7, -68, 43, 79, -11, -49, 81, 182, 8, -196, -150, 70, 197, 57, -138, -87, 54, 54, -39, -43, 77, 25, -192, -265, -77, 156, 161, -92, -292, -194, 82, 246, 137, -87, -150, -27, 97, 70, 37, 56, 46, -21, -47, 22, 50, 34, 30, 17, 52, 115, 94, -38, -97, -9, 28, -63, -109, 1, 133, 31, -234, -301, -62, 165, 141, -48, -128, -45, 17, -25, -55, 47, 120, 34, -106, -59, 142, 179, -24, -182, -79, 180, 274, 92, -131, -141, -41, -3, -7, -9, 3, -3, -40, -68, -86, -55, 10, 27, -55, -83, -8, 38, 38, -6, -71, -116, -55, 113, 231, 116, -121, -134, 43, 176, 68, -115, -94, 109, 172, 28, -160, -171, 77, 161, -11, -134, 12, 224, 136, -148, -257, -23, 239, 173, -94, -234, -79, 192, 184, -72, -263, -157, 146, 230, 91, -121, -175, -46, 113, 192, 60, -91, -115, 0, 99, 45, -87, -138, -63, 14, 46, -2, -29, -40, -4, -28, -72, -17, 103, 130, -7, -86, -44, 57, 65, -18, -21, 34, 40, -19, -9, 58, 63, -20, -87, -56, 49, 104, 30, -54, -54, 23, 17, -16, 48, 125, 42, -151, -146, 47, 177, 60, -117, -101, 71, 114, -40, -131, -57, 85, 63, -65, -135, -77, 18, 68, 2, -137, -156, -71, 86, 151, -10, -187, -162, 42, 195, 110, -77, -121, 2, 94, 55, 3, 25, 60, -7, -63, 25, 81, 44, -47, -118, -58, 68, 98, 21, -35, -37, -2, 57, 54, -17, -39, -17, 25, 24, -4, 18, 38, 13, -40, -52, 26, 159, 98, -114, -175, 8, 199, 153, -40, -86, 27, 98, 35, -54, -33, 24, 41, 12, -58, -51, 30, 41, -66, -125, -72, 28, 56, -1, -73, -123, -66, 49, 86, 10, -67, -39, 30, 58, 2, -15, 29, 82, 69, 11, -10, 42, 57, 4, -33, -20, 25, 38, 13, -36, -64, -56, -46, -32, 20, 79, 30, -60, -88, -46, 0, 40, 38, -10, -47, -15, 92, 129, -11, -180, -148, 38, 139, 64, -76, -106, -12, 67, 28, -47, -22, 79, 66, -47, -112, -37, 96, 81, -36, -104, -7, 143, 120, -47, -165, -59, 92, 105, -15, -103, -48, 31, 7, -61, -71, -30, 53, 47, -31, -60, -6, 54, 33, -38, -45, 24, 72, 16, -63, -66, 1, 49, 19, -11, -14, -18, -22, -34, 2, 52, 13, -48, -34, 69, 115, -6, -109, -40, 121, 148, 30, -71, -17, 78, 53, -31, -65, 6, 98, 106, 57, -10, -28, 4, 44, 42, 17, -34, -29, 2, 27, 65, 33, -16, -67, -25, 83, 123, 30, -91, -95, 5, 94, 58, -28, -81, -17, 36, -9, -69, -44, 26, 41, 11, -34, -9, 42, 33, 4, -31, -48, -13, 45, 71, 27, -51, -62, -23, 17, 47, 21, -33, -68, -45, 34, 72, -6, -85, -51, 46, 78, -24, -102, -85, -20, 11, -31, -95, -61, 12, 9, -57, -77, -25, 46, 14, -65, -82, -40, 23, 10, -35, -50, 2, 47, 42, -27, -81, -20, 50, 61, 8, -12, 22, 44, 1, -29, -1, 36, 45, 30, 27, 30, 0, -7, 15, 9, -10, 5, 33, 31, 2, -18, -25, 1, 46, 55, 21, -37, -33, 15, 62, 23, -41, -24, 63, 90, 8, -54, -1, 91, 83, 7, -15, 44, 58, 14, -31, -13, 50, 51, 7, -6, 25, 49, 4, -46, 8, 52, 20, -28, -1, 37, 11, -34, -11, 64, 82, 14, -38, -29, 24, 39, -13, -50, -24, 15, 41, 25, -18, -25, -9, 18, -1, -24, -21, 27, 30, -28, -46, -1, 52, 12, -55, -42, 39, 69, 9, -59, -33, 39, 16, -74, -69, 28, 85, 19, -82, -55, 30, 53, -38, -98, -24, 49, 24, -27, -45, -7, -16, -51, -35, 7, 30, 15, -21, -28, 6, -7, -46, -55, -31, -31, -40, -51, -33, 0, -15, -40, -38, -6, -8, -51, -33, -16, -10, -7, -35, -19, 35, 41, -16, -51, 5, 87, 79, -6, -52, 21, 90, 46, -30, -28, 53, 80, 21, -41, -20, 74, 76, -25, -63, -3, 79, 49, -34, -29, 43, 77, 31, -5, -6, 32, 58, 6, -46, 10, 67, 39, -14, -30, 34, 89, 76, 24, 2, 48, 54, 15, -18, -4, 34, 23, -11, -16, 19, 36, 12, -38, -27, 23, 70, 44, 2, -5, 22, 26, -11, -16, 8, 13, 3, -20, -39, -32, 3, 41, 12, -26, -15, 11, 23, -18, -58, -39, 10, 12, -43, -59, -2, 26, -11, -46, -42, -3, 18, -19, -63, -59, -30, -26, -38, -34, -1, -8, -42, -52, -26, 2, -12, -39, -46, -20, -28, -46, -39, -8, -1, -9, -7, 2, 8, -5, -32, -20, 10, -7, -20, -22, -18, -6, -13, -32, -45, -14, 26, 11, -24, -18, 9, 22, 0, -18, -6, 30, 38, 5, -27, -14, 33, 51, 12, -7, 2, 19, 17, 9, 15, 25, 35, 43, 18, 9, 23, 16, 7, 12, 17, 25, 25, 25, 5, -31, -30, 17, 43, 18, 4, 22, 16, 6, -11, -4, 8, 28, 20, -20, -4, 48, 39, -8, -24, 3, 21, 7, 0, -11, 10, 27, -8, -28, 12, 37, 22, -17, -17, 14, 37, 16, -8, -5, 3, 20, 7, -18, -10, 19, 6, -42, -50, -10, 9, -17, -35, -31, -9, 13, 14, 10, 0, -6, -19, -23, -21, -4, 7, -2, -12, -11, 13, 18, -9, -30, -4, 1, -15, -20, -22, -1, 1, -3, -9, -38, -30, 3, -1, -4, -18, -22, 0, 3, -23, -25, -19, -10, -2, -3, 2, -3, -11, -9, 3, 10, 27, 16, -14, -23, -19, 10, 9, -5, -8, -12, -7, -3, -2, -6, 4, 8, 20, 11, 17, 17, -5, -6, 2, 9, -1, 2, -2, 9, 10, 4, -12, -8, 4, 18, 14, -1, 16, 19, 12, -12, -25, -12, 18, 16, -1, -5, 6, 21, 2, -8, -2, 24, 12, -21, -18, -4, 8, -1, -9, -4, 8, 24, 5, -10, -5, 11, 2, -2, 6, 5, -9, -1, -11, -30, -9, 14, 21, 13, 4, -6, 23, 20, -3, 0, 13, 16, 6, -3, -10, -4, -10, -21, -15, 6, 14, 6, 2, 12, 8, -15, -10, 7, 2, -2, -6, 0, 11, 7, -8, -13, 3, 22, 18, 3, -8, -16, -19, -23, -27, -30, -5, -7, -5, 0, 8, 11, 4, -4, -13, -1, 7, -2, -14, 2, 4, 12, -4, -14, -4, 11, -2, -21, -8, 11, 19, -3, -22, -19, 10, 1, -24, -30, -13, -2, -11, -14, -8, 18, 18, -15, -21, -1, -1, 4, 1, -10, -1, 1, -9, -17, -11, 13, 12, 10, -2, -4, 5, 4, -3, -5, -3, 6, 25, 12, -4, -11, 8, 6, -11, -14, 8, 5, -12, -6, 7, 37, 25, 1, -14, -1, 28, 27, -6, 9, 27, 3, -7, -2, 19, 13, 15, 14, -6, -13, -2, -7, -8, -13, -10, 9, 10, 1, -18, -22, -13, -18, -19, -17, -3, 7, -5, -12, 10, 9, -3, -3, 2, 5, 1, 4, 13, 23, 1, -7, -2, 1, 5, -6, -14, 2, 9, -3, -1, 13, 27, 2, -1, -11, -13, -1, 0, 9, 14, 16, -2, -18, -11, -15, -23, -2, 17, 14, -1, -4, -13, -16, -12, -21, -9, 15, -6, -16, -17, -13, -3, 4, -7, -7, 7, 13, 19, 3, -4, -3, 21, 16, 17, 0, -2, 7, -6, -7, -13, 0, 4, 4, 2, 14, 8, 5, 4, 3, -2, -3, 8, 9, 4, 1, 0, 2, 20, 26, 19, 4, -6, -10, -22, -10, 1, 3, 1, -2, -3, -14, -12, -15, -18, -6, 6, -6, -8, -12, -19, -6, -15, -20, -9, 7, -6, -4, -1, 7, 16, 5, -2, 1, 1, 3, 5, -2, 8, 8, 5, 4, 15, 14, 11, 8, 1, -2, 2, 9, 16, 23, 3, 0, 2, -7, -15, 1, 21, 0, -6, 14, -1, -10, -24, -41, -12, -1, -18, -22, -12, -3, -3, -15, -22, -12, 5, -2, -20, -13, 2, -10, -8, 3, 19, 16, 10, 11, 23, 20, 5, -1, 3, 8, 13, 6, -1, 13, 13, 15, 19, 6, 5, 27, 31, 8, 6, 13, 14, 8, 7, 11, 12, 23, 18, -3, -9, -8, 5, 12, 4, -18, -8, 4, -11, -14, 6, 9, -3, 0, -5, -6, -2, -8, -14, -1, -7, -4, 16, 22, 1, -6, 12, 6, -1, -1, -11, 0, 19, 4, -9, -1, 6, 1, -8, -5, -13, -7, 8, 0, -7, -20, -7, 8, 3, 2, 16, -2, -6, 3, -3, -5, -10, -4, -2, -4, 1, -3, -10, -16, -20, -2, -2, -13, -22, -5, 2, -14, -11, -8, 8, 8, -4, -15, -13, -12, -9, 1, 4, 3, -1, 4, 6, 3, 0, 0, 5, 5, 11, 5, 14, 28, 8, 1, 18, 7, 13, 16, 14, 26, 13, 8, 4, 20, 32, 13, 2, 28, 43, 24, 7, 12, 27, 7, -5, 2, 14, 3, -6, 4, 9, 5, 0, 6, 22, 20, -10, -24, -21, -17, 0, -8, -17, -13, -4, -1, 4, 4, 4, -2, -21, -26, -19, -17, -14, -11, -2, 2, -1, -7, -4, -2, -8, -8, 11, 3, -17, -17, -2, -9, -13, -4, 7, 6, -2, -6, 12, 15, -20, -28, -1, 15, 4, -5, -3, 14, 27, 12, -3, 1, 17, 14, 7, 7, 2, -3, -18, -23, -17, -11, -7, -13, -16, -1, 4, 0, -17, -25, -13, -5, -6, -15, -22, -13, 1, 4, 12, -1, -11, 8, -5, -14, -11, 4, 7, -1, -3, -1, 6, 8, 12, 18, 21, 18, 13, 18, 16, 0, -1, 5, 5, 1, 9, 24, 31, 32, 26, 31, 22, 10, 4, 6, 8, 6, -9, -11, 11, 11, 11, -2, -17, -3, 7, -3, -10, -13, -6, -3, -15, 6, 9, -3, -10, -2, 9, -1, -10, -16, -6, -1, -7, -5, 7, 10, 12, 7, -18, -19, -22, -7, 5, 5, 0, -10, -10, 1, 2, -4, -7, -9, -1, 9, 10, 4, -8, -10, -13, -1, 17, 9, -11, 7, 20, 7, -10, -19, -10, -3, -8, -9, -4, -5, -13, -15, -11, -1, -7, -14, -7, -8, -13, -8, -19, -30, -14, 5, 2, -11, -12, -6, -10, -5, 5, 6, -6, -16, -7, -8, -17, -7, -5, 0, -3, 1, 13, 18, 4, 14, 29, 16, 7, 8, 14, 8, 7, 8, 7, 4, -2, -6, -1, 13, 11, 20, 21, 12, 5, 4, 1, -9, 0, 5, 9, 9, 15, 4, 0, -3, 8, 12, 9, 12, -4, 0, 5, -1, 7, 1, -6, 5, 7, -5, -3, -17, -7, 6, 6, 5, -4, -19, -15, -8, -3, -3, -11, -3, 11, 17, 16, 1, -5, -1, -1, 2, -7, -17, -7, -4, -3, 7, 13, 12, -1, 5, 13, 1, -9, -9, -11, -3, 5, -5, -16, -10, -2, 7, 10, -7, -17, -6, 1, -4, -10, -13, -10, -9, -8, 0, -2, -6, -14, -18, -5, -5, -9, -8, -4, 1, 18, 4, -1, 1, 7, 15, 8, -1, -12, -7, 2, 12, 11, 6, 8, 3, 7, 7, 0, -6, -2, -3, 8, 4, -2, -14, -19, 3, 8, 5, -2, -3, -6, -4, -5, -12, -21, -9, 0, -18, -11, -2, 6, 7, 0, -2, -6, -6, -6, 1, 6, -4, -10, 3, 18, 16, 18, 16, 12, 8, 10, 9, 4, -1, 5, 10, 14, 5, 0, 2, 9, 9, 9, 4, 2, 5, 4, -6, -15, -11, 4, 13, 17, 13, 3, -2, 3, 5, 10, 0, -1, -4, 3, 12, 6, 0, -7, -2, 5, 16, 9, -4, 0, 4, -2, -8, -9, -20, -5, -2, -1, 3, -4, -18, -6, 8, 4, -5, -16, -13, -10, 0, 4, -3, -10, -7, 2, -1, -13, -21, -5, 7, 6, 4, -7, -7, -10, 0, 10, 3, 0, -4, -3, 8, -2, 1, 4, 12, 15, 8, 3, -3, -7, 1, 10, 13, 3, -10, -6, -6, 6, 14, -4, -3, 2, -2, 2, -18, -24, -4, -9, -3, -11, -17, 1, 8, 6, 5, 1, -5, -14, -8, -4, -7, -12, -5, 1, 5, 3, -11, -18, -17, -10, -3, -6, -12, -1, 18, 26, 21, 7, -18, -22, -8, -2, -3, 6, 22, 19, 15, 3, -2, 1, 7, 24, 23, 14, 5, -4, -2, 1, 18, 9, -3, -3, 3, 11, 25, 19, 1, -7, -2, -4, -13, 0, 8, 10, 16, 22, 25, 13, -5, -15, -6, -12, -15, -21, -18, -2, -1, -11, -29, -13, -7, -3, 3, 0, 4, -3, -9, -9, -12, -19, -9, -3, -1, 4, 3, -8, -13, -1, 4, -2, -2, -5, -5, 11, 19, 10, 13, 16, 11, 9, 1, -5, 6, 6, 2, 8, 0, 5, 16, 7, 20, 17, 16, 11, -8, -6, 10, 18, 27, 9, 0, 10, 5, 2, -9, -10, 6, 3, -9, -4, 1, 2, 5, 2, -6, -10, -3, -8, -3, 8, 7, -2, -6, -8, -8, -6, -11, -10, -1, 7, 8, -2, -10, 1, 3, 1, -8, -12, -3, -5, -5, -2, -3, 8, -1, -19, -16, -28, -19, 4, 3, 10, 12, 12, 4, -1, -12, -12, -13, -8, 0, 6, 11, 11, 13, -1, -8, -14, -10, -11, -7, 1, 0, -5, -10, -3, 6, 7, 0, -2, -2, 6, -1, -9, -4, -5, -3, -14, -11, 1, -3, 1, 1, 2, 0, -2, -2, -2, -9, -13, 5, 13, 10, 12, 11, 13, 18, 8, -6, -6, 5, 1, -1, 14, 18, 19, 17, 23, 24, 18, 16, 7, 2, -3, 5, 4, -3, 14, 4, -1, 0, -2, 1, 6, -2, -5, -1, -4, 5, 3, 0, -5, -4, -5, -14, -6, -10, -16, -8, -1, -17, -22, -12, 3, 1, -3, 0, -7, -3, 0, 0, 1, 3, 5, 3, 10, 5, 0, 2, 6, 17, 17, 9, 3, 2, 1, 3, -9, -10, 11, 16, 17, 9, -8, -10, -2, -7, -8, 6, 13, 4, 11, 1, -7, 2, 2, 8, 15, 11, 8, -1, -9, -8, -2, -7, -2, 7, 6, 7, 7, 4, -6, -7, -7, -17, -8, -11, -10, 3, 3, -1, -1, -3, -6, -11, -15, -27, -23, -21, -26, -3, 3, -3, -9, -4, 2, -5, -15, -23, -14, -11, -9, -5, -9, 2, 8, 2, -3, 0, -8, -16, -5, -6, -9, -8, -4, 0, 8, 6, -2, -4, 4, 5, 0, 5, -5, -7, 0, 3, -4, -3, 2, 4, 17, 20, 14, 15, 23, 15, 7, 3, -2, 10, 14, 24, 32, 16, 8, 6, 16, 20, 3, -1, 5, 7, 0, 4, 7, 3, 1, 1, -2, -4, 4, 7, -1, 0, -1, -7, -9, -5, -9, -4, -2, -4, -2, 5, -6, -6, -5, -12, -12, -9, -8, -14, -4, 0, 8, 17, 10, 7, 7, 10, 4, 5, 7, 4, 6, 4, -1, 1, -4, -4, 1, 4, 0, -7, -5, 2, 15, 8, 3, 6, -2, 0, 5, -4, -7, -5, 8, 7, 0, -1, 2, 3, -8, -8, 4, 16, -9, -3, 14, 6, 8, 1, -9, 1, 4, -8, 0, 6, -1, 3, 3, -1, 10, 9, 3, 9, 4, 0, 7, -1, 2, 8, -4, -7, -5, -1, -1, 3, 3, 9, 5, 4, 1, 9, 12, -2, -2, -16, -8, 8, 11, 0, -13, -15, -20, -14, -11, -16, -6, 8, 6, 2, -10, -10, -6, -11, -15, -10, -11, -15, 0, -6, -9, -17, -15, -14, -27, -29, -10, -5, -7, -1, -5, 0, 3, -7, 3, 3, 1, 3, 3, 0, 1, 8, 7, 16, 12, -7, -3, 0, 6, 12, 11, 11, 7, 3, 2, 4, 0, 5, 6, -5, 1, 12, 20, 19, 15, 7, 4, 6, 4, 6, 6, 2, 0, 5, -1, -1, 1, 0, -1, -5, -2, -4, 5, 10, 2, 3, -4, -8, -6, -13, -4, -4, -10, -10, -8, -7, -2, -11, -23, -25, -21, -9, -7, -6, -6, -14, -5, -7, -9, -16, -10, -4, -11, -4, -7, -2, 1, -6, -1, -1, -2, 6, 10, 3, 1, 3, 11, 17, 9, -2, -3, 11, 21, 9, 9, 21, 23, 19, 14, 13, 10, 5, 8, 11, 16, 13, 15, 16, 13, 12, 1, -4, 6, 6, -2, 3, 0, -1, 4, 2, 17, 21, 8, -5, -1, -1, -6, 8, 4, -1, 7, 9, 7, -4, -13, -10, -5, -15, -8, -2, -11, -7, -9, -15, -16, -14, -10, -8, -5, -17, -8, -2, -11, -6, -4, -8, -7, -9, -5, -5, -6, -16, -14, -3, 1, -9, -15, -14, -6, 1, -1, 9, 2, -8, -4, -2, -4, -5, -2, -6, 3, 6, 4, 10, 6, 6, -5, -10, -16, -13, -2, 2, 0, -6, -1, 1, 4, 9, 2, 5, -3, -10, 4, 13, 9, 12, 7, 2, 11, 6, -1, 9, 9, 15, 13, 9, -2, 1, 10, 10, 4, -3, 3, 20, 26, 20, 7, 1, 3, 5, 5, 3, -4, 1, 1, 2, 12, 9, 1, 0, -5, -2, 7, -2, -5, 1, -7, -6, 2, -7, -14, -6, 1, 9, 6, 11, 1, 2, 2, 11, 5, -9, -1, 2, 6, -5, -9, -5, -7, 0, -5, -17, -9, -3, -2, -3, -6, -9, -13, -12, -8, -3, -11, -5, -17, -20, -16, -10, -3, -14, -18, -11, -6, -4, -7, -6, -6, -1, 1, -3, -3, 2, 7, 6, 1, -1, 6, 11, 15, 20, 17, 8, 4, 7, 11, 5, 2, 9, 8, 3, 9, 9, 4, 2, -2, 4, 7, 7, 4, 4, 7, 7, 7, 0, -2, 5, 17, 10, 1, -2, 1, 6, 15, 8, -2, -9, -7, 5, 0, 5, 6, 2, -2, 0, -8, -13, -5, 9, 1, -7, 0, -3, -4, -8, -7, -7, -16, -11, -8, -3, -3, -5, -2, -5, -1, -2, -5, -11, -15, -14, -3, 2, 1, -3, 2, -1, -2, 8, 1, -2, 5, 5, 6, 7, 2, 0, 6, -2, -2, 1, -1, 8, 11, 5, 0, 4, 7, -2, -1, -4, -2, 9, 19, 11, 7, 1, 2, 6, -4, -4, 0, -8, -9, 0, 3, 9, 19, 8, -8, -5, -1, 2, 8, 9, 15, 15, -2, -12, -6, -10, -6, -1, -13, -19, -6, 5, 5, 8, 3, -8, -12, -14, -8, 1, -8, -11, 1, -13, -11, -4, -5, -8, -3, 0, -7, -2, -4, -1, -1, 7, 9, -3, -9, -5, 3, 8, 7, 2, 10, 5, 4, 4, -2, -1, -1, 10, 12, 14, 12, 8, 8, 6, 2, 5, 7, 2, 4, -2, -9, -2, 6, 2, 0, 3, 2, -6, -6, 5, 12, 9, -4, -2, 2, -4, -2, -5, -14, -10, 1, 3, -4, -2, -2, -4, -1, -2, -4, -3, -2, 7, 11, -2, -3, -7, -13, -3, 4, 3, -9, -4, 1, -7, -1, 2, 5, 2, -7, -4, 3, -5, -3, -2, -2, 2, -2, -8, -10, 2, 12, 11, 3, -6, -7, 0, 1, -2, 3, -3, 0, 12, 15, 10, 3, 2, 3, -8, -5, 10, 7, -6, 1, 4, 7, 12, 6, 8, 8, 7, 3, 1, -2, -2, 2, 0, -3, -7, -1, 6, 4, 3, -3, -4, 2, -6, 0, 2, -5, -7, -3, 5, 6, 5, -4, 3, -2, -3, -1, -4, -11, -16, -5, 6, 10, 3, 1, 4, -12, -5, 2, 2, -6, -6, 0, -1, 9, 7, 0, 0, -5, 1, -1, 6, 2, 0, 4, -5, 1, -1, 4, 2, -2, -2, -5, -7, 1, 10, 4, 6, -2, 3, 4, 8, 13, 8, 11, 5, 4, 0, -9, -15, -11, -7, -3, -2, 2, -1, 3, 2, -5, -4, -3, 0, 2, 1, -14, -14, 0, 3, -6, -10, -1, -5, -4, -9, -13, -2, -8, -4, 7, -1, -6, -1, 4, -2, -1, 1, 5, 7, -6, -6, -10, -7, 0, 1, 0, 2, 17, 11, 7, 4, 4, 5, -2, -3, -3, 2, 1, -1, 0, -2, -11, -1, 9, 4, -7, -12, -7, -4, 1, 3, -2, -1, 4, -3, -5, -3, -5, -4, -2, 3, -3, 2, 3, 0, 2, 4, 8, 12, 12, 4, 1, 2, 6, 9, 8, 1, 1, 7, 5, 1, -2, 12, 14, 0, -4, -3, 1, 0, 1, -1, -2, -6, -6, 0, -2, -10, -8, -6, -9, -4, -9, -4, 5, 6, -4, -20, -12, -3, 6, -3, -9, -3, -2, 0, 1, 6, 3, 3, 3, 1, 0, 0, 7, 9, 3, -3, -10, -6, -1, 0, -2, 1, 7, 8, 8, 11, 3, 3, 4, 2, 2, -2, -8, -5, 3, -3, 2, 1, -5, -9, -10, -4, -7, -2, -1, 7, 4, 1, 11, 4, -2, -9, -8, 0, 2, -1, 10, 7, -4, 4, 19, 15, 4, 4, 2, 6, 13, 5, -7, -7, -6, -5, -8, -11, -3, 1, 1, -10, -8, -7, 0, -1, -2, 8, 6, 5, -3, 1, -4, 2, -2, -13, -5, -7, -10, -7, 0, 6, -1, -1, -1, 4, 5, -5, -4, -3, 0, 0, 11, 15, 5, 0, -3, 3, 0, 6, -1, -4, 4, 2, -1, -6, -5, -7, -6, 1, 2, -3, -5, -9, -6, -10, -8, -11, -6, -2, -1, -2, 0, 2, -3, 13, 19, 9, 5, -4, -3, -3, -1, 4, 11, 10, 6, 3, 0, -6, -8, -4, -2, -5, 1, 2, -1, 3, 2, 0, -1, -3, -4, 4, 11, 8, 5, -2, 1, -2, 3, 4, -1, 0, -3, -5, -12, -1, 2, 2, 2, 0, 3, -2, -3, -1, 0, 2, 3, 5, 7, 9, 8, 12, 10, 0, 7, 5, 4, 7, 0, -6, -6, 0, 1, 0, 7, 8, 8, 9, 4, -6, -7, -5, -8, -3, -8, -9, 1, 13, 10, 3, 4, 2, 1, 4, 4, -6, -5, -4, -8, 6, 2, -6, -8, -3, -4, -4, -5, -12, -3, 5, 6, 1, -5, -4, -3, -3, -4, -4, -7, -14, -14, -7, -6, -7, -13, -6, -3, -1, -1, 2, 11, 7, 3, -2, -4, -3, -6, -4, 3, 3, -1, -1, -1, 9, 8, -2, -5, -4, -1, 8, 10, 8, 11, 8, 2, 0, 4, -2, -3, 2, -2, 1, -3, 0, 2, 0, 7, 3, 3, -1, -4, 4, 5, 2, 3, 1, -4, -2, 4, 2, -2, 1, 3, -1, -2, -3, -5, 5, 4, 2, 6, 5, 3, 5, 5, -10, -8, -7, -7, -1, -4, 0, 4, 4, 1, 1, 2, 2, 2, 0, 3, -1, -5, -4, 5, 9, 9, 6, 5, -2, 0, -2, -4, -3, -1, 1, 2, 0, 0, 1, -1, 4, -3, -1, 5, -1, -2, 3, 3, -8, 1, 1, 0, 5, -2, 1, 1, -8, -5, 6, 4, -7, -6, -5, -1, 2, 3, 2, 3, 8, 4, -4, -6, -8, -9, -8, 2, 2, -2, 1, -1, 3, -3, -6, -6, 0, 4, 2, 17, 13, -5, 1, 2, -2, -4, -1, 0, 2, -9, -13, 0, 1, -1, 1, 13, 8, 1, 2, 0, -2, -5, 0, -2, 9, 8, 3, 3, 6, 6, -5, 8, 2, -5, 0, 2, 1, -5, 1, -3, -5, 0, -1, -3, -4, 2, 0, -1, 1, -5, -1, 7, -7, -6, -2, -4, -3, 4, 3, -1, 3, -3, 0, 3, -4, -4, -3, -5, -1, 3, 1, -4, 1, 3, -2, -4, -3, -9, -8, 6, 4, 0, 0, 3, 2, 1, 3, 0, 3, 2, 7, 5, 4, 7, 2, 4, 2, 1, -1, -1, 1, 2, 6, 5, 3, 2, 4, 1, 1, -1, 4, 1, -3, -1, -5, -2, -2, -3, 2, 3, 1, -1, 1, 4, 0, 0, -4, -11, 2, 4, -1, 1, -3, 0, -1, 3, -4, -3, 3, 0, 0, 0, 6, 10, 7, 3, -1, -3, -1, -4, -9, 0, -3, -2, 3, 2, -2, 2, 4, -6, -1, 3, -2, -6, -3, 1, 0, 0, -3, -3, -4, -4, -3, 6, 2, -7, 4, 7, -5, -3, 8, -3, -8, -4, -6, -8, -2, 1, 0, 4, -2, -2, 3, 4, -1, -1, 4, -4, 0, 6, 1, -3, 0, -2, -6, 3, -2, -3, 0, 4, -2, -3, 2, -4, -2, 5, 4, -3, -4, -2, -5, 5, -4, -7, 1, 6, 4, 0, 4, -11, -3, 2, -6, -5, -5, 0, -1, 4, -3, -10, 4, 2, -9, -2, 2, -4, -4, -1, 5, 8, 6, -2, -4, 3, 3, 2, 7, 6, 3, 8, 11, 7, 8, 14, 11, 8, 11, 6, 7, 4, 3, -2, 5, 12, 8, 5, 0, 3, 2, -1, 1, 2, 2, -5, 1, -1, -3, 3, -3, -4, -5, -6, -2, 3, 3, 4, 1, -7, 0, -3, -11, -10, -5, -5, -11, -10, -7, -3, -4, -2, -1, -7, -6, -7, -4, -2, -8]}}